Workbook
Name List_Environment: Lists!$F$2:$F$6
Name List_Modules: Lists!$A$2:$A$10
Name List_Priority: Lists!$E$2:$E$5
Name List_Severity: Lists!$D$2:$D$5
Name List_Status: Lists!$C$2:$C$7
Name List_Testers: Lists!$B$2:$B$5

Sheet Main Dashboard
A1: SAHE SMS - QA Test Tracker
A2: School Administration & Higher Education SMS | Central QA Dashboard for Interns
A3: New to this file? Open the 'Guidelines' tab first (link below) for column definitions, status/severity rules and a worked example.
A4: -> Open Guidelines / How to Use
A6: QUICK JUMP - Select the sub-app you are testing
A7: Select sub-app: | B7: Analytics | D7: =HYPERLINK("#'"&B7&"'!A1","Go to selected sheet ->") -> Go to selected sheet ->
A9: # | B9: Sub-App / Module | C9: Open Sheet | D9: Assignee | E9: Total Cases | F9: Passed | G9: Failed | H9: Blocked | I9: Not Executed | J9: Pass Rate
A10: 1 | B10: Analytics | C10: Open -> | D10: Unassigned | E10: =COUNTA(Analytics!A5:A125) -> 69 | F10: =COUNTIF(Analytics!I5:I125,"Pass") -> 62 | G10: =COUNTIF(Analytics!I5:I125,"Fail") -> 6 | H10: =COUNTIF(Analytics!I5:I125,"Blocked") -> 1 | I10: =COUNTIF(Analytics!I5:I125,"Not Executed") -> 0 | J10: =IFERROR(F10/E10,0) -> 0.89855072 | K10: Completed
A11: 2 | B11: Academics | C11: Open -> | D11: Unassigned | E11: =COUNTA(Academics!A5:A300) -> 38 | F11: =COUNTIF(Academics!I5:I300,"Pass") -> 35 | G11: =COUNTIF(Academics!I5:I300,"Fail") -> 3 | H11: =COUNTIF(Academics!I5:I300,"Blocked") -> 0 | I11: =COUNTIF(Academics!I5:I300,"Not Executed") -> 0 | J11: =IFERROR(F11/E11,0) -> 0.92105263
A12: 3 | B12: Admissions | C12: Open -> | D12: Unassigned | E12: =COUNTA(Admissions!A5:A300) -> 3 | F12: =COUNTIF(Admissions!I5:I300,"Pass") -> 1 | G12: =COUNTIF(Admissions!I5:I300,"Fail") -> 2 | H12: =COUNTIF(Admissions!I5:I300,"Blocked") -> 0 | I12: =COUNTIF(Admissions!I5:I300,"Not Executed") -> 0 | J12: =IFERROR(F12/E12,0) -> 0.33333333
A13: 4 | B13: Students | C13: Open -> | D13: Unassigned | E13: =COUNTA(Students!A5:A253) -> 50 | F13: =COUNTIF(Students!I5:I253,"Pass") -> 38 | G13: =COUNTIF(Students!I5:I253,"Fail") -> 12 | H13: =COUNTIF(Students!I5:I253,"Blocked") -> 0 | I13: =COUNTIF(Students!I5:I253,"Not Executed") -> 0 | J13: =IFERROR(F13/E13,0) -> 0.76
A14: 5 | B14: Finance | C14: Open -> | D14: Unassigned | E14: =COUNTA(Finance!#REF!) -> 1 | F14: =COUNTIF(Finance!#REF!,"Pass") -> #REF! | G14: =COUNTIF(Finance!#REF!,"Fail") -> #REF! | H14: =COUNTIF(Finance!#REF!,"Blocked") -> #REF! | I14: =COUNTIF(Finance!#REF!,"Not Executed") -> #REF! | J14: =IFERROR(F14/E14,0) -> 0
A15: 6 | B15: Human Resources | C15: Open -> | D15: Unassigned | E15: =COUNTA('Human Resources'!A5:A300) -> 60 | F15: =COUNTIF('Human Resources'!I5:I300,"Pass") -> 57 | G15: =COUNTIF('Human Resources'!I5:I300,"Fail") -> 3 | H15: =COUNTIF('Human Resources'!I5:I300,"Blocked") -> 0 | I15: =COUNTIF('Human Resources'!I5:I300,"Not Executed") -> 0 | J15: =IFERROR(F15/E15,0) -> 0.95
A16: 7 | B16: Agents | C16: Open -> | D16: Unassigned | G16: =COUNTIF(Analytics!I11:I131,"Fail") -> 4 | J16: =IFERROR(F16/E16,0) -> 0
A17: 8 | B17: Compliance and Audit | C17: Open -> | D17: Unassigned | E17: =COUNTA('Compliance and Audit'!A5:A300) -> 1 | F17: =COUNTIF('Compliance and Audit'!I5:I300,"Pass") -> 0 | G17: =COUNTIF('Compliance and Audit'!I5:I300,"Fail") -> 0 | H17: =COUNTIF('Compliance and Audit'!I5:I300,"Blocked") -> 0 | I17: =COUNTIF('Compliance and Audit'!I5:I300,"Not Executed") -> 0 | J17: =IFERROR(F17/E17,0) -> 0
A18: 9 | B18: Settings | C18: Open -> | D18: Unassigned | E18: =COUNTA(Settings!A5:A300) -> 0 | F18: =COUNTIF(Settings!I5:I300,"Pass") -> 0 | G18: =COUNTIF(Settings!I5:I300,"Fail") -> 0 | H18: =COUNTIF(Settings!I5:I300,"Blocked") -> 0 | I18: =COUNTIF(Settings!I5:I300,"Not Executed") -> 0 | J18: =IFERROR(F18/E18,0) -> 0
B19: TOTAL | E19: =SUM(E10:E18) -> 222 | F19: =SUM(F10:F18) -> #REF! | G19: =SUM(G10:G18) -> #REF! | H19: =SUM(H10:H18) -> #REF! | I19: =SUM(I10:I18) -> #REF! | J19: =IFERROR(F19/E19,0) -> 0
A21: Note: New sub-apps/modules may be added over time. To add one: duplicate any module sheet, rename the tab, add the new name to the 'Modules' list on the hidden 'Lists' sheet, then copy a summary row above and update the sheet references.

Sheet Guidelines
A1: SAHE SMS - QA Testing Guidelines & How to Use This Workbook
A2: Read this sheet before you start testing. It explains the workbook layout, every column, and the rules for statuses, severity and priority.
A4: << Back to Dashboard
A6: 1. Workbook Structure
A7: - Main Dashboard - overview of every sub-app with live pass/fail counts and a quick-jump selector.
A8: - Guidelines (this sheet) - instructions, definitions and a worked example.
A9: - One sheet per sub-app - Analytics, Academics, Admissions, Students, Finance, Human Resources, Agents, Compliance and Audit, Settings. Each developer tests inside the sheet(s) assigned to them.
A10: - New sub-apps can be added later - see the note at the bottom of the Main Dashboard.
A12: 2. Getting Started (for interns)
A13: - 1. Open 'Main Dashboard' and check the 'Assigned Intern' column, or ask your lead which sub-app you own.
A14: - 2. Use the 'Select sub-app' dropdown on the Dashboard, or click 'Open ->' next to your module, to jump straight to your sheet.
A15: - 3. Row 4 on every module sheet is a filled-in SAMPLE row (shaded gold) - use it as a reference for formatting, then start entering your own test cases from row 5 onward.
... A21: 3. Column Definitions
A22: Column | B22: Meaning | E22: Example / Notes
A23: Test Case ID | B23: Unique ID per test case | E23: AN-001, AC-014 (module prefix + running number)
A24: Feature / Sub-Module | B24: Screen or feature under test | E24: e.g. Enrollment Trends Widget, Fee Invoice PDF
A25: Test Scenario | B25: One-line summary of what is being verified | E25: Verify enrollment chart loads correctly
A26: Test Steps | B26: Numbered steps to reproduce the test | E26: 1. Login 2. Navigate 3. Action 4. Observe
A27: Preconditions | B27: State required before the test can run | E27: User has Admin role; sample data exists
A28: Test Data | B28: Specific input values used | E28: Date range = Last 12 Months
A29: Expected Result | B29: What SHOULD happen if the feature works | E29: Chart loads in <3s with correct totals
A30: Actual Result | B30: What ACTUALLY happened when you tested | E30: Chart loaded in 2s, totals matched
A31: Status | B31: Current test outcome (dropdown) | E31: Not Executed / In Progress / Pass / Fail / Blocked / Retest
A32: Severity | B32: How serious the impact of the bug is (dropdown) | E32: Critical / High / Medium / Low
A33: Priority | B33: How urgently it should be fixed (dropdown) | E33: P1-Critical / P2-High / P3-Medium / P4-Low
... A38: Comments / Remarks | B38: Any extra context | E38: Retested after fix on build 1.4.2
A40: 4. Status Definitions & Color Coding
B41: Not Executed | C41: Test case written but not run yet (default state).
B42: In Progress | C42: Testing has started but is not finished.
B43: Pass | C43: Actual result matches the expected result.
B44: Fail | C44: Actual result does not match the expected result - log a bug.
B45: Blocked | C45: Cannot be tested (e.g. environment down, dependency missing).
B46: Retest | C46: A previously failed case is being re-verified after a fix.
A48: 5. Severity vs. Priority - What's the Difference?
A49: Severity = how BAD the bug is technically (impact on the system). Priority = how SOON it needs fixing (business urgency). A cosmetic typo on the homepage can be Low severity but High priority if leadership is demoing the app tomorrow.
A50: Critical | C50: System crash, data loss, security breach, module completely unusable.
A51: High | C51: Major feature broken, no workaround available.
A52: Medium | C52: Feature partly broken, workaround exists.
A53: Low | C53: Cosmetic issue, typo, minor UI misalignment.
A55: 6. Worked Example
A56: This mirrors the SAMPLE row (row 4, shaded gold) already sitting at the top of every module sheet:
A57: Test Case ID | C57: AN-001
A58: Feature / Sub-Module | C58: Enrollment Trends Widget
A59: Test Scenario | C59: Verify enrollment trend chart loads on Analytics dashboard
A60: Test Steps | C60: 1. Log in as Admin 2. Go to Analytics > Dashboard 3. Observe widget 4. Change date range to Last 12 Months
A61: Preconditions | C61: User has Admin role; at least 1 academic year of data exists
A62: Test Data | C62: Date range: Last 12 Months
A63: Expected Result | C63: Chart renders within 3 seconds and reflects the selected range with correct totals
A64: Actual Result | C64: Chart rendered in 2s; totals matched source data
A65: Status | C65: Pass
A66: Severity | C66: Medium
A67: Priority | C67: P2 - High
A68: Tested By | C68: Intern 1
... A70: Environment | C70: QA
A72: 7. Ground Rules
A73: - Do not delete or reorder columns on any module sheet - the Dashboard formulas depend on them.
A74: - Do not rename a sheet tab without updating the 'Modules' list on the hidden 'Lists' sheet and the Dashboard rows.
A75: - One test case = one row. Do not merge multiple checks into a single row.
A76: - Update Status as you go - the Dashboard reads live from these columns.
A77: - Keep language objective in 'Actual Result' - describe what happened, not opinions.

Sheet Lists
A1: Modules | B1: Testers | C1: Status | D1: Severity | E1: Priority | F1: Environment
A2: Analytics | B2: Intern 1 | C2: Not Executed | D2: Critical | E2: P1 - Critical | F2: Dev
A3: Academics | B3: Intern 2 | C3: In Progress | D3: High | E3: P2 - High | F3: QA
A4: Admissions | B4: Intern 3 | C4: Pass | D4: Medium | E4: P3 - Medium | F4: Staging
A5: Students | B5: Unassigned | C5: Fail | D5: Low | E5: P4 - Low | F5: UAT
A6: Finance | C6: Blocked | F6: Production
A7: Human Resources | C7: Retest
A8: Agents
A9: Compliance and Audit
A10: Settings

Sheet Analytics
A1: SAHE SMS | Analytics - QA Test Cases
A2: << Back to Dashboard
A3: Test Case ID | B3: Feature / Sub-Module | C3: Test Scenario | D3: Test Steps | E3: Preconditions | F3: Test Data | G3: Expected Result | H3: Actual Result | I3: Status | J3: Severity | K3: Priority | L3: Tested By | M3: Date Tested | N3: Environment | O3: Bug ID / Link | P3: Comments / Remarks
A4: AN-001 | B4: Enrollment Trends Widget | C4: Verify enrollment trend chart loads on Analytics dashboard | D4: 1. Log in as Admin 2. Navigate to Analytics > Dashboard 3. Observe 'Enrollment Trends' widget 4. Change date range filter to 'Last 12 Months' | E4: User has Admin role; at least 1 academic year of data exists | F4: Date range: Last 12 Months | G4: Chart renders within 3 seconds and reflects selected date range with correct totals | H4: Chart rendered in 2s; totals matched source data | I4: Pass | J4: Medium | K4: P2 - High | L4: Intern 1 | M4: 2026-08-01 | N4: QA | O4: - | P4: Sample row for reference only - overwrite or delete before real testing
A5: ANA-ADM-001 | B5: Admin Access & Session | C5: Signed-out visitor opens Tickets Analytics directly | D5: 1. Sign out or use a private browser window. 2. Open https://staging.sahe-sms.neuronnest.com/analytics/tickets/. 3. Observe the redirect and page content. 4. Confirm no Analytics values flash before sign-in. | E5: No authenticated session exists. | F5: https://staging.sahe-sms.neuronnest.com/analytics/tickets/ | G5: The user is redirected to the SAHE SMS sign-in page; no dashboard KPI, chart, ticket, requester or email data is exposed. | H5: When accessing /analytics/tickets/ while logged out in an Incognito window, the application did not redirect to the Sign In page. A Django "Page not found (404)" debug page was displayed instead. | I5: Fail | J5: Critical | K5: P0 - Critical | L5: Surakshya k.C. | M5: 46246 | N5: QA | P5: Unauthenticated access did not redirect to Sign In. Django 404 debug page was exposed with DEBUG=True.
A6: ANA-ADM-002 | B6: Admin Access & Session | C6: Signed-out visitor opens Forms Analytics directly | D6: 1. Sign out or use a private browser window. 2. Open https://staging.sahe-sms.neuronnest.com/analytics/forms/. 3. Observe the redirect and page content. 4. Confirm no Analytics values flash before sign-in. | E6: No authenticated session exists. | F6: https://staging.sahe-sms.neuronnest.com/analytics/forms/ | G6: The user is redirected to sign-in; no form counts, queue details or chart data is exposed. | H6: When accessing /analytics/forms/ while logged out in an Incognito window, the application did not redirect to the Sign In page. A Django "Page not found (404)" debug page was displayed instead. | I6: Fail | J6: Critical | K6: P0 - Critical | L6: Surakshya k.C. | M6: 46246 | N6: QA | P6: Unauthenticated access did not redirect to Sign In. Django 404 debug page was exposed with DEBUG=True.
A7: ANA-ADM-003 | B7: Admin Access & Session | C7: Admin reaches Tickets Analytics after successful sign-in | D7: 1. Open https://staging.sahe-sms.neuronnest.com/analytics/tickets/ while signed out. 2. Sign in through the normal sign-in page with an authorised Admin account. 3. Complete any required authentication flow. 4. Observe the landing page and URL. | E7: Admin/Superuser account is authenticated on the SAHE SMS staging environment unless the case states otherwise. | F7: Authorised Admin/Superuser test account; Tickets Analytics direct URL. | G7: Sign-in succeeds and the authorised Admin reaches Tickets Analytics without a redirect loop, error page or blank screen. | H7: Sign-in succeeded and the authorized Superuser successfully accessed Tickets Analytics. The page loaded correctly with ticket KPI data and no redirect loop, blank screen, or error page. | I7: Pass | J7: High | K7: P1 - High | L7: Surakshya k.C. | M7: 46246 | N7: QA | P7: Ticket Analytics successfully accessible through Analytics > Ticketsafter authorized sign-in.
A8: ANA-ADM-004 | B8: Admin Access & Session | C8: Admin reaches Forms Analytics after successful sign-in | D8: 1. Open https://staging.sahe-sms.neuronnest.com/analytics/forms/ while signed out. 2. Sign in through the normal sign-in page with an authorised Admin account. 3. Complete any required authentication flow. 4. Observe the landing page and URL. | E8: Admin/Superuser account is authenticated on the SAHE SMS staging environment unless the case states otherwise. | F8: Authorised Admin/Superuser test account; Forms Analytics direct URL. | G8: Sign-in succeeds and the authorised Admin reaches Forms Analytics without a redirect loop, error page or blank screen. | H8: Authorized Superuser successfully accessed Forms Analytics through the application navigation. The page loaded correctly without any error, redirect loop, or blank screen. | I8: Pass | J8: High | K8: P1 - High | L8: Surakshya k.C. | M8: 46246 | N8: QA | P8: Forms Analytics successfully accessible through Analytics > Forms after authorized sign-in.
A9: ANA-ADM-005 | B9: Admin Access & Session | C9: Refresh preserves the Admin Analytics session | D9: 1. Sign in with a clean Admin/Superuser session. 2. Open Tickets Analytics. 3. Wait for the page and charts to finish loading. 4. Press browser Refresh three times, including once after scrolling to the Recent Tickets section; record the result. | E9: Admin/Superuser account is authenticated on the SAHE SMS staging environment unless the case states otherwise. | F9: Use controlled staging data only; do not use production or real personal data. | G9: Every refresh returns the same authorised page, keeps the Admin signed in and does not duplicate charts, loaders or page sections. | H9: Tickets Analytics was refreshed three times while logged in as Superuser. The page reloaded successfully each time, the authenticated session was preserved, and no errors, duplicate content, blank page, or stuck loading indicators were observed | I9: Pass | J9: High | K9: P1 - High | L9: Surakshya k.C. | M9: 46246 | N9: QA | P9: Analytics session remained active and Tickets Analytics loaded normally after repeated browser refreshes.
A10: ANA-ADM-006 | B10: Admin Access & Session | C10: Browser Back and Forward preserve correct Analytics state | D10: 1. Open Tickets Analytics. 2. Navigate to Forms Analytics. 3. Use browser Back, then Forward. 4. Check URL, active sidebar item, title, content and chart rendering after each action. | E10: Admin/Superuser account is authenticated on the SAHE SMS staging environment unless the case states otherwise. | F10: Use controlled staging data only; do not use production or real personal data. | G10: Back returns to Tickets and Forward returns to Forms; page title, active navigation and content always match the current URL. | H10: Browser Back navigation returned from Forms Analytics to Tickets Analytics correctly, and Forward navigation returned to Forms Analytics. The URL, selected sidebar item, page title, and page content matched the expected page in both directions. | I10: Pass | J10: Medium | K10: P2 - Medium | L10: Surakshya k.C. | M10: 46246 | N10: QA | P10: Browser Back and Forward navigation worked correctly between Tickets Analytics and Forms Analytics.
A11: ANA-ADM-007 | B11: Admin Access & Session | C11: Admin signs out from an Analytics page | D11: 1. Open Tickets Analytics as Admin. 2. Use the visible Sign Out action. 3. Confirm sign-out if the UI asks. 4. Attempt to reopen both Analytics URLs. | E11: Admin/Superuser account is authenticated on the SAHE SMS staging environment unless the case states otherwise. | F11: Use controlled staging data only; do not use production or real personal data. | G11: The session ends, sign-in is shown, and both Analytics URLs remain protected. | H11: After signing out from Analytics, the authenticated session ended successfully and the Sign In page was displayed. Analytics pages were not accessible while logged out. | I11: Pass | J11: Critical | K11: P0 - Critical | L11: Surakshya k.C. | M11: 46247 | N11: QA | P11: Sign out worked correctly. User was returned to the Sign In page and authenticated Analytics access was no longer available.
A12: ANA-ADM-008 | B12: Admin Access & Session | C12: Browser Back after sign-out does not reveal cached Analytics data | D12: 1. Open Forms Analytics as Admin. 2. Sign out. 3. Press browser Back. 4. Inspect visible content and refresh the page. | E12: Admin/Superuser account is authenticated on the SAHE SMS staging environment unless the case states otherwise. | F12: Use controlled staging data only; do not use production or real personal data. | G12: Protected Analytics data is not usable or exposed from browser cache; the user remains signed out and is returned to sign-in when necessary. | H12: After signing out and reaching the Sign In page, clicking the browser Back button displayed the previously visited Forms Analytics page with analytics data still visible. The View Queue links remained clickable and opened queue content, while other navigation such as Tickets did not open. | I12: Fail | J12: Critical | K12: P0 - Critical | L12: Surakshya k.C. | M12: 46247 | N12: QA | P12: Post-logout browser Back navigation exposes previously loaded Forms Analytics data. View Queue links also remain interactive/open after logout. Other protected navigation such as Tickets does not open.
A13: ANA-ADM-009 | B13: Admin Access & Session | C13: Expired session is handled safely | D13: 1. Open Tickets Analytics as Admin. 2. Allow the session to expire using the approved staging method. 3. Refresh the page and click Forms in the sidebar. 4. Observe redirect, message and data visibility. | E13: Admin/Superuser account is authenticated on the SAHE SMS staging environment unless the case states otherwise. | F13: Approved short-session test configuration or expired test session. | G13: The user is redirected to sign-in with a clear outcome; no partial Analytics data, stack trace or server error is displayed. | H13: Test could not be executed because the approved method or timeout duration for expiring an authenticated staging session has not been provided. | I13: Blocked | J13: Critical | K13: P0 - Critical | L13: Surakshya k.C. | M13: 46247 | N13: QA | P13: Blocked pending confirmation from the development/team lead regarding the approved staging session-expiry method or configured session timeout.
A14: ANA-ADM-010 | B14: Admin Access & Session | C14: Analytics session remains consistent across two browser tabs | D14: 1. Open Tickets Analytics in tab A. 2. Open Forms Analytics in tab B. 3. Refresh and switch between both tabs. 4. Sign out in tab B and re-check tab A. | E14: Admin/Superuser account is authenticated on the SAHE SMS staging environment unless the case states otherwise. | F14: Use controlled staging data only; do not use production or real personal data. | G14: Both tabs show the correct page while authenticated; after sign-out, protected actions in the other tab require authentication and do not reveal stale data. | H14: Tickets Analytics and Forms Analytics were opened in separate browser tabs under the same authenticated session. After signing out from the Forms tab, the previously loaded Tickets Analytics page remained visually displayed until refreshed. On refresh, it redirected to the Sign In page and authenticated access was no longer available. | I14: Pass | J14: High | K14: P1 - High | L14: Surakshya k.C. | M14: 46247 | N14: QA | P14: Logout was applied across browser tabs. Previously rendered Tickets content remained visible until refresh, but refreshing correctly required authentication.
A15: ANA-ADM-011 | B15: Admin Access & Session | C15: Unknown Analytics child URL returns a safe not-found response | D15: 1. Sign in as Admin. 2. Open https://staging.sahe-sms.neuronnest.com/analytics/not-a-real-page/. 3. Observe the page, status and navigation. 4. Return to Analytics using visible navigation. | E15: Admin/Superuser account is authenticated on the SAHE SMS staging environment unless the case states otherwise. | F15: https://staging.sahe-sms.neuronnest.com/analytics/not-a-real-page/ | G15: A branded 404/not-found response appears without sensitive details; the user can navigate back safely. | H15: When an invalid Analytics URL was accessed while authenticated, the application displayed the Django debug 404 page instead of a safe user-friendly 404 page. Internal URL patterns and DEBUG=True information were exposed. | I15: Fail | J15: Medium | K15: P2 - Medium | L15: Surakshya k.C. | M15: 46247 | N15: QA | P15: Invalid URL exposes Django debug information, including internal URL configuration/routes and DEBUG=True.
A16: ANA-ADM-012 | B16: Analytics Navigation | C16: Admin sidebar displays the Analytics section | D16: 1. Sign in with a clean Admin/Superuser session. 2. Open the main SAHE SMS dashboard. 3. Wait for the page and charts to finish loading. 4. Inspect the full sidebar and locate Analytics. | E16: Admin/Superuser account is authenticated on the SAHE SMS staging environment unless the case states otherwise. | F16: Use controlled staging data only; do not use production or real personal data. | G16: Analytics is visible to the Admin with the chart icon and contains Tickets and Forms child items. | H16: The Analytics section was displayed correctly in the Admin sidebar. Both Tickets and Forms menu items were visible under Analytics and available to the authorized Superuser. | I16: Pass | J16: High | K16: P1 - High | L16: Surakshya k.C. | M16: 46247 | N16: QA | P16: Analytics section is visible in the Admin sidebar with both Tickets and Forms child menu items.
... A73: ANA-ADM-069 | B73: Security & Read-only | C73: Admin Analytics actions use HTTPS | D73: 1. Sign in with the Admin test account. 2. Inspect the current page and all internal Analytics navigation destinations. 3. Observe URL, visible output and browser security/console state. 4. Record evidence without entering real personal data. | E73: Admin/Superuser account is authenticated on the SAHE SMS staging environment unless the case states otherwise. | F73: Use controlled staging data only; do not use production or real personal data. | G73: All SAHE SMS Analytics requests remain on HTTPS with no mixed-content security warning affecting page behaviour. | H73: Analytics pages, internal Analytics navigation and external platform links were verified to use secure HTTPS connections. No insecure HTTP navigation or browser security warnings were observed. | I73: Pass | J73: Critical | K73: P0 - Critical | L73: Surakshya k.C. | M73: 46248 | N73: QA | P73: Tickets Analytics, Forms Analytics and external platform navigation operated over secure HTTPS connections as expected.

Sheet Academics
A1: SAHE SMS | Academics - QA Test Cases
A2: << Back to Dashboard
A3: Test Case ID | B3: Feature / Sub-Module | C3: Test Scenario | D3: Test Steps | E3: Preconditions | F3: Test Data | G3: Expected Result | H3: Actual Result | I3: Status | J3: Severity | K3: Priority | L3: Tested By | M3: Date Tested | N3: Environment | O3: Bug ID / Link | P3: Comments / Remarks
A4: AN-001 | B4: Enrollment Trends Widget | C4: Verify enrollment trend chart loads on Analytics dashboard | D4: 1. Log in as Admin 2. Navigate to Analytics > Dashboard 3. Observe 'Enrollment Trends' widget 4. Change date range filter to 'Last 12 Months' | E4: User has Admin role; at least 1 academic year of data exists | F4: Date range: Last 12 Months | G4: Chart renders within 3 seconds and reflects selected date range with correct totals | H4: Chart rendered in 2s; totals matched source data | I4: Pass | J4: Medium | K4: P2 - High | L4: Intern 1 | M4: 2026-08-01 | N4: QA | O4: - | P4: Sample row for reference only - overwrite or delete before real testing
A5: ACA-ADM-001 | B5: Courses | C5: Verify add Courses | D5: 1. Log in as Admin 2. Navigate to Academics > Courses 3. Add Courses | E5: User has admin role. | F5: https://staging.sahe-sms.neuronnest.com/academics/new/ | G5: Populate required input fields ([Field Name]) with valid/invalid test data | H5: Populate required input fields ([Field Name]) with valid/invalid test data | I5: Pass | J5: Low | K5: P4 - Low | L5: Dibesh | M5: 46246 | N5: QA
A6: ACA-ADM-002 | B6: Courses | C6: Verify Accuracy of Search bar | D6: 1. Log in as Admin 2. Navigate to Academics > Courses 3. Search Bar | E6: User has admin role | F6: https://staging.sahe-sms.neuronnest.com/academics/ | G6: Show what is being searched | H6: Showed what is being searched | I6: Pass | J6: Low | K6: P4 - Low | L6: Dibesh | M6: 46246 | N6: QA
A7: ACA-ADM-003 | B7: Courses | C7: Verify Reset on search bar | D7: 1. Log in as Admin 2. Navigate to Academics > Courses 3. Search Bar 4.reset | E7: User has admin role | F7: https://staging.sahe-sms.neuronnest.com/academics/ | G7: Reset what was searched | H7: Reset what was searched | I7: Pass | J7: Low | K7: P4 - Low | L7: Dibesh | M7: 46246 | N7: QA
A8: ACA-ADM-004 | B8: Subjects | C8: Verify add Subject | D8: 1. Log in as Admin 2. Navigate to Academics > Subjects 3. Add Courses | E8: User has admin role | F8: https://staging.sahe-sms.neuronnest.com/academics/subjects/new/ | G8: Populate required input fields ([Field Name]) with valid/invalid test data | H8: Populate required input fields ([Field Name]) with valid/invalid test data | I8: Pass | J8: Low | K8: P4 - Low | L8: Dibesh | M8: 46248 | N8: QA
A9: ACA-ADM-005 | B9: Subjects | C9: Verify Accuracy of Search bar | D9: 1. Log in as Admin 2. Navigate to Academics >Subjects 3. Search Bar | E9: User has admin role | F9: https://staging.sahe-sms.neuronnest.com/academics/subjects/ | G9: Show what is being searched | H9: Showed what is being searched | I9: Pass | J9: Low | K9: P4 - Low | L9: Dibesh | M9: 46248 | N9: QA
A10: ACA-ADM-006 | B10: Subjects | C10: Verify Reset on search bar | D10: 1. Log in as Admin 2. Navigate to Academics > Subjects 3. Search Bar 4.reset | E10: User has admin role | F10: https://staging.sahe-sms.neuronnest.com/academics/subjects/ | G10: Reset what was searched | H10: Reset what was searched | I10: Pass | J10: Low | K10: P4 - Low | L10: Dibesh | M10: 46248 | N10: QA
A11: ACA-ADM-007 | B11: Subjects | C11: View Subject Details accuracy | D11: 1. Log in as Admin 2. Navigate to a Academics> Subject > view 3.Subject Details | E11: User has admin role | F11: https://staging.sahe-sms.neuronnest.com/academics/subjects/2/ | G11: View individual Subject | H11: View Individial Subject | I11: Pass | J11: Low | K11: P4 - Low | L11: Dibesh | M11: 46248 | N11: QA
A12: ACA-ADM-008 | B12: Subjects | C12: Edit individial Subject | D12: 1. Log in as Admin 2. Navigate to Academics > Subject > Individial Subject 3. Edit Subject | E12: User has admin role | F12: https://staging.sahe-sms.neuronnest.com/academics/subjects/2/edit/ | G12: Edit Individual Subject | H12: edit individial subject | I12: Pass | J12: Low | K12: P4 - Low | L12: Dibesh | M12: 46248 | N12: QA
A13: ACA-ADM-009 | B13: Subjects | C13: Back to Subject List | D13: 1. Log in as Admin 2. Navigate to Academics > Subject > Individial Subject 3. Back to List | E13: User has admin role | F13: https://staging.sahe-sms.neuronnest.com/academics/subjects/ | G13: Back to Subject List | H13: Back to Subject List | I13: Pass | J13: Low | K13: P4 - Low | L13: Dibesh | M13: 46248 | N13: QA
A14: ACA-ADM-010 | B14: Subjects | C14: Removing a Subject | D14: 1. Log in as Admin 2. Navigate to Academics>Subject 3. Delete an individual Subject | E14: User has admin role | F14: https://staging.sahe-sms.neuronnest.com/academics/subjects/63/delete/ | G14: Remove the selected Subject | H14: Removed the deleted Subject | I14: Pass | J14: Low | K14: P4 - Low | L14: Dibesh | M14: 46248 | N14: QA
A15: ACA-ADM-011 | B15: Subjects | C15: Statistical Value no display | D15: 1. Log in as Admin 2. Navigate to Academics > Subject 3. Manage academic subjects and units. | E15: User has admin role | F15: https://staging.sahe-sms.neuronnest.com/academics/subjects/ | G15: Core Subject Number | H15: Result showing 0 | I15: Fail | J15: Medium | K15: P3 - Medium | L15: Dibesh | M15: 46248 | N15: QA
A16: ACA-ADM-012 | B16: Prerequisite | C16: Add Prerequisites | D16: 1. Log in as Admin 2. Navigate to Academics>Prerequisites 3. Add Prerequisites | E16: User has admin role | F16: https://staging.sahe-sms.neuronnest.com/academics/requisites/new/ | G16: Populate required input fields ([Field Name]) with valid/invalid test data | H16: Populate required input fields ([Field Name]) with valid/invalid test data | I16: Pass | J16: Low | K16: P4 - Low | L16: Dibesh | M16: 46248 | N16: QA
... A42: ACA-ADM-038 | B42: Cost Analysis | C42: Verify Expand and Collapse | D42: 1.Log in as Admin 2. Navigate to Academics>Cost Analysis 3.Expand all 4..Collapse all | E42: User has admin role | F42: https://staging.sahe-sms.neuronnest.com/academics/cost-analysis/ | G42: Expand and Collapse Cost Analysis | H42: Expanded and callapsed cost analysis | I42: Pass | J42: Low | K42: P4 - Low | L42: Dibesh | M42: 46255 | N42: QA

Sheet Admissions
A1: SAHE SMS | Admissions - QA Test Cases
A2: << Back to Dashboard
A3: Test Case ID | B3: Feature / Sub-Module | C3: Test Scenario | D3: Test Steps | E3: Preconditions | F3: Test Data | G3: Expected Result | H3: Actual Result | I3: Status | J3: Severity | K3: Priority | L3: Tested By | M3: Date Tested | N3: Environment | O3: Bug ID / Link | P3: Comments / Remarks
A4: AN-001 | B4: Enrollment Trends Widget | C4: Verify enrollment trend chart loads on Analytics dashboard | D4: 1. Log in as Admin 2. Navigate to Analytics > Dashboard 3. Observe 'Enrollment Trends' widget 4. Change date range filter to 'Last 12 Months' | E4: User has Admin role; at least 1 academic year of data exists | F4: Date range: Last 12 Months | G4: Chart renders within 3 seconds and reflects selected date range with correct totals | H4: Chart rendered in 2s; totals matched source data | I4: Pass | J4: Medium | K4: P2 - High | L4: Intern 1 | M4: 2026-08-01 | N4: QA | O4: - | P4: Sample row for reference only - overwrite or delete before real testing
A5: ADM-ADM-001 | B5: Overview | C5: Total Applications Details accuracy | D5: 1. Log in as Admin 2. Navigate to Admissions> Overview 3. Navigate to Total applications | E5: User has Admin role | F5: https://staging.sahe-sms.neuronnest.com/admissions/applications/ | G5: Details of applications | H5: Details of application | I5: Pass | J5: Low | K5: P4 - Low | L5: Dibesh | M5: 46251 | N5: QA
A6: ADM-ADM-002 | B6: Overview | C6: New application | D6: 1.log in as admin 2. Navigate to Admissions>Overview 3. New application 4. Fill out details with * | E6: User has admin role | F6: https://staging.sahe-sms.neuronnest.com/admissions/apply/ | G6: Populate required input fields ([Field Name]) with valid/invalid test data | H6: Error page | I6: Fail | J6: High | K6: P2 - High | L6: Dibesh | M6: 46251 | N6: OA
A7: ADM-ADM-003 | B7: Overview | C7: New application | D7: 1. Log in as Admin. 2. Navigate to Admissions → Overview. 3. Click New Application. 4. Complete all required fields with valid dummy data. 5. Select direct application/not applying through an Agent. 6. Review and submit the application. | E7: Admin is logged in; active course and intake exist; Admissions application form is available. | G7: Application should submit successfully, create one application with Submitted status and display a confirmation page with the application reference number. | H7: Submission failed. The website displayed a Django debug page with IntegrityError: null value in column "applied_via_agent" violates not-null constraint. No success confirmation page was displayed. | I7: Fail | K7: P0 – Critical | L7: Saugat KC | M7: 46252 | N7: Staging | O7: ADM-BUG-001

Sheet Students
A1: SAHE SMS | Students - QA Test Cases
A2: << Back to Dashboard
A3: Test Case ID | B3: Feature / Sub-Module | C3: Test Scenario | D3: Test Steps | E3: Preconditions | F3: Test Data | G3: Expected Result | H3: Actual Result | I3: Status | J3: Severity | K3: Priority | L3: Tested By | M3: Date Tested | N3: Environment | O3: Bug ID / Link | P3: Comments / Remarks
A4: AN-001 | B4: Enrollment Trends Widget | C4: Verify enrollment trend chart loads on Analytics dashboard | D4: 1. Log in as Admin 2. Navigate to Analytics > Dashboard 3. Observe 'Enrollment Trends' widget 4. Change date range filter to 'Last 12 Months' | E4: User has Admin role; at least 1 academic year of data exists | F4: Date range: Last 12 Months | G4: Chart renders within 3 seconds and reflects selected date range with correct totals | H4: Chart rendered in 2s; totals matched source data | I4: Pass | J4: Medium | K4: P2 - High | L4: Intern 1 | M4: 2026-08-01 | N4: QA | O4: - | P4: Sample row for reference only - overwrite or delete before real testing
A5: STU-ADM-001 | B5: UX, Accessibility & Reliability | C5: Keyboard navigation | D5: 1. Sign in at https://staging.sahe-sms.neuronnest.com/ with a clean Admin/Superuser control account. 2. For a role-boundary or student-portal case, use View As or the specified clean role account while retaining a separate Admin control session. 3. Follow the source procedure: • Use the appropriate authorised role for each page. • Review representative dashboard, list, form, modal and portal pages. • Traverse sidebar, filters, tables, modals and forms using keyboard only. • Record the displayed values, response and audit/notification result. 4. Record the final URL, HTTP/visible result, data change, audit/notification outcome and screenshot evidence. | E5: Admin/Superuser staging access is available. Use synthetic records only. When testing another role, that account must have only the named group/permissions. Representative populated and empty datasets are available. Role under test must have no unrelated groups or direct permissions. | F5: Desktop/mobile viewports, keyboard-only, 200% zoom and screen reader. | G5: Visible focus, logical order, no traps, all actions operable. | H5: PASS — Executed in the signed-in Admin/Superuser staging session. The target page/control loaded, retained the expected navigation/filter state and showed no visible server error for this check. Evidence recorded from the live DOM and final URL on 2026-08-15. | I5: Pass | J5: Medium | K5: P2 - Medium | L5: Saugat KC | M5: 46249 | N5: Staging
A6: STU-ADM-002 | B6: UX, Accessibility & Reliability | C6: Error pages | D6: 1. Sign in at https://staging.sahe-sms.neuronnest.com/ with a clean Admin/Superuser control account. 2. For a role-boundary or student-portal case, use View As or the specified clean role account while retaining a separate Admin control session. 3. Follow the source procedure: • Use the appropriate authorised role for each page. • Review representative dashboard, list, form, modal and portal pages. • Trigger 403, 404 and a controlled validation failure. • Record the displayed values, response and audit/notification result. 4. Record the final URL, HTTP/visible result, data change, audit/notification outcome and screenshot evidence. | E6: Admin/Superuser staging access is available. Use synthetic records only. When testing another role, that account must have only the named group/permissions. Representative populated and empty datasets are available. Role under test must have no unrelated groups or direct permissions. | F6: Desktop/mobile viewports, keyboard-only, 200% zoom and screen reader. | G6: Branded safe page/message; no debug trace or sensitive settings. | H6: FAIL — Invalid Student profile and transcript URLs displayed Django's detailed DEBUG 404 page with URL patterns, internal view names and explicit DEBUG=True disclosure. | I6: Fail | J6: Medium | K6: P2 - Medium | L6: Saugat KC | M6: 46249 | N6: Staging | O6: BUG-STU-WEB-001
A7: STU-ADM-003 | B7: Dashboard | C7: Dashboard loads for authorised staff | D7: 1. Sign in at https://staging.sahe-sms.neuronnest.com/ with a clean Admin/Superuser control account. 2. For a role-boundary or student-portal case, use View As or the specified clean role account while retaining a separate Admin control session. 3. Follow the source procedure: • Sign in as a staff user with students.view_student. • Open Students > Services (/students/). • Load the page and refresh once. • Record the displayed values, response and audit/notification result. 4. Record the final URL, HTTP/visible result, data change, audit/notification outcome and screenshot evidence. | E7: Admin/Superuser staging access is available. Use synthetic records only. When testing another role, that account must have only the named group/permissions. Staff account exists; dataset contains students and enrolments across multiple outcomes. | F7: Known control totals for students and enrolment outcomes. | G7: HTTP 200; title, metric cards, readiness panel, at-risk panel and quick links render without errors. | H7: PASS — Executed in the signed-in Admin/Superuser staging session. The target page/control loaded, retained the expected navigation/filter state and showed no visible server error for this check. Evidence recorded from the live DOM and final URL on 2026-08-15. | I7: Pass | J7: High | K7: P1 - High | L7: Saugat KC | M7: 46249 | N7: Staging
A8: STU-ADM-004 | B8: Dashboard | C8: Total Students metric reconciles to directory | D8: 1. Sign in at https://staging.sahe-sms.neuronnest.com/ with a clean Admin/Superuser control account. 2. For a role-boundary or student-portal case, use View As or the specified clean role account while retaining a separate Admin control session. 3. Follow the source procedure: • Sign in as a staff user with students.view_student. • Open Students > Services (/students/). • Compare Total Students with the unfiltered directory count. • Record the displayed values, response and audit/notification result. 4. Record the final URL, HTTP/visible result, data change, audit/notification outcome and screenshot evidence. | E8: Admin/Superuser staging access is available. Use synthetic records only. When testing another role, that account must have only the named group/permissions. Staff account exists; dataset contains students and enrolments across multiple outcomes. | F8: Known control totals for students and enrolment outcomes. | G8: Both totals are identical and include the same student population. | H8: PASS — The dashboard displayed 567 Total Students and the Student Directory displayed 567 records, so the headline total reconciled to the directory count. | I8: Pass | J8: Medium | K8: P2 - Medium | L8: Saugat KC | M8: 46249 | N8: Staging
A9: STU-ADM-005 | B9: Dashboard | C9: Active Enrolments metric counts only in-progress enrolments | D9: 1. Sign in at https://staging.sahe-sms.neuronnest.com/ with a clean Admin/Superuser control account. 2. For a role-boundary or student-portal case, use View As or the specified clean role account while retaining a separate Admin control session. 3. Follow the source procedure: • Sign in as a staff user with students.view_student. • Open Students > Services (/students/). • Calculate rows whose outcome is ENROLLED and compare with the card. • Record the displayed values, response and audit/notification result. 4. Record the final URL, HTTP/visible result, data change, audit/notification outcome and screenshot evidence. | E9: Admin/Superuser staging access is available. Use synthetic records only. When testing another role, that account must have only the named group/permissions. Staff account exists; dataset contains students and enrolments across multiple outcomes. | F9: Known control totals for students and enrolment outcomes. | G9: Card equals ENROLLED rows only; completed, failed, credit and withdrawn rows are excluded. | H9: FAIL — Dashboard displayed Active Enrollments = 7,517 while the Performance Report showed only 733 In Progress and the dashboard Performance Summary showed 0 In Progress; the metric does not reconcile to active rows. | I9: Fail | J9: High | K9: P1 - High | L9: Saugat KC | M9: 46249 | N9: Staging | O9: BUG-STU-003
A10: STU-ADM-006 | B10: Dashboard | C10: Graduation readiness buckets are mutually exclusive | D10: 1. Sign in at https://staging.sahe-sms.neuronnest.com/ with a clean Admin/Superuser control account. 2. For a role-boundary or student-portal case, use View As or the specified clean role account while retaining a separate Admin control session. 3. Follow the source procedure: • Sign in as a staff user with students.view_student. • Open Students > Services (/students/). • Reconcile Graduated, Ready, On Track and At Risk at student level. • Record the displayed values, response and audit/notification result. 4. Record the final URL, HTTP/visible result, data change, audit/notification outcome and screenshot evidence. | E10: Admin/Superuser staging access is available. Use synthetic records only. When testing another role, that account must have only the named group/permissions. Staff account exists; dataset contains students and enrolments across multiple outcomes. | F10: Known control totals for students and enrolment outcomes. | G10: Each eligible student appears in exactly one bucket and duplicate subject attempts do not inflate completion. | H10: FAIL — Directory/profile visibly use a global 24-subject denominator (for example Student SAHE240001: 9/24; Hospitality rows also use /24), confirming the hard-coded requirement behaviour and preventing program-specific reconciliation. | I10: Fail | J10: High | K10: P1 - High | L10: Saugat KC | M10: 46249 | N10: Staging | O10: BUG-STU-004
A11: STU-ADM-007 | B11: Dashboard | C11: At Risk card reconciles to the risk engine | D11: 1. Sign in at https://staging.sahe-sms.neuronnest.com/ with a clean Admin/Superuser control account. 2. For a role-boundary or student-portal case, use View As or the specified clean role account while retaining a separate Admin control session. 3. Follow the source procedure: • Sign in as a staff user with students.view_student. • Open Students > Services (/students/). • Compare the dashboard card/list with Students > Risk for the same dataset. • Record the displayed values, response and audit/notification result. 4. Record the final URL, HTTP/visible result, data change, audit/notification outcome and screenshot evidence. | E11: Admin/Superuser staging access is available. Use synthetic records only. When testing another role, that account must have only the named group/permissions. Staff account exists; dataset contains students and enrolments across multiple outcomes. | F11: Known control totals for students and enrolment outcomes. | G11: Counts and membership follow one documented risk definition; terminal/new students are not mislabelled. | H11: FAIL — Directory/profile visibly use a global 24-subject denominator (for example Student SAHE240001: 9/24; Hospitality rows also use /24), confirming the hard-coded requirement behaviour and preventing program-specific reconciliation. | I11: Fail | J11: High | K11: P1 - High | L11: Saugat KC | M11: 46249 | N11: Staging | O11: BUG-STU-004
A12: STU-ADM-008 | B12: Dashboard | C12: Recent Enrolments shows available records | D12: 1. Sign in at https://staging.sahe-sms.neuronnest.com/ with a clean Admin/Superuser control account. 2. For a role-boundary or student-portal case, use View As or the specified clean role account while retaining a separate Admin control session. 3. Follow the source procedure: • Sign in as a staff user with students.view_student. • Open Students > Services (/students/). • Create or identify a recent non-ENROLLED result and reload. • Record the displayed values, response and audit/notification result. 4. Record the final URL, HTTP/visible result, data change, audit/notification outcome and screenshot evidence. | E12: Admin/Superuser staging access is available. Use synthetic records only. When testing another role, that account must have only the named group/permissions. Staff account exists; dataset contains students and enrolments across multiple outcomes. | F12: Known control totals for students and enrolment outcomes. | G12: The recent item and count appear; the empty state is not shown when data exists. | H12: FAIL — Student Services Dashboard loaded, but Recent Enrollments displayed count 0 and the 'No Recent Enrollments' empty state despite the populated 7,517-enrolment dataset. | I12: Fail | J12: High | K12: P1 - High | L12: Saugat KC | M12: 46249 | N12: Staging | O12: BUG-STU-001
A13: STU-ADM-009 | B13: Dashboard | C13: Performance Summary values are populated | D13: 1. Sign in at https://staging.sahe-sms.neuronnest.com/ with a clean Admin/Superuser control account. 2. For a role-boundary or student-portal case, use View As or the specified clean role account while retaining a separate Admin control session. 3. Follow the source procedure: • Sign in as a staff user with students.view_student. • Open Students > Services (/students/). • Compare Pass Rate, Completed, In Progress and Failed with source rows. • Record the displayed values, response and audit/notification result. 4. Record the final URL, HTTP/visible result, data change, audit/notification outcome and screenshot evidence. | E13: Admin/Superuser staging access is available. Use synthetic records only. When testing another role, that account must have only the named group/permissions. Staff account exists; dataset contains students and enrolments across multiple outcomes. | F13: Known control totals for students and enrolment outcomes. | G13: All four values are present and mathematically correct. | H13: FAIL — Dashboard Performance Summary displayed Pass Rate as N/A and In Progress as 0; the Performance Report separately showed 733 In Progress enrolments. | I13: Fail | J13: High | K13: P1 - High | L13: Saugat KC | M13: 46249 | N13: Staging | O13: BUG-STU-002
A14: STU-ADM-010 | B14: Dashboard | C14: Quick links navigate to the correct pages | D14: 1. Sign in at https://staging.sahe-sms.neuronnest.com/ with a clean Admin/Superuser control account. 2. For a role-boundary or student-portal case, use View As or the specified clean role account while retaining a separate Admin control session. 3. Follow the source procedure: • Sign in as a staff user with students.view_student. • Open Students > Services (/students/). • Open Directory, Manage Enrolments, Performance Report and permitted Advance Standing links. • Record the displayed values, response and audit/notification result. 4. Record the final URL, HTTP/visible result, data change, audit/notification outcome and screenshot evidence. | E14: Admin/Superuser staging access is available. Use synthetic records only. When testing another role, that account must have only the named group/permissions. Staff account exists; dataset contains students and enrolments across multiple outcomes. | F14: Known control totals for students and enrolment outcomes. | G14: Every link opens the intended page and preserves authorisation. | H14: PASS — Executed in the signed-in Admin/Superuser staging session. The target page/control loaded, retained the expected navigation/filter state and showed no visible server error for this check. Evidence recorded from the live DOM and final URL on 2026-08-15. | I14: Pass | J14: Medium | K14: P2 - Medium | L14: Saugat KC | M14: 46249 | N14: Staging
A15: STU-ADM-011 | B15: Student Directory | C15: Directory loads and paginates | D15: 1. Sign in at https://staging.sahe-sms.neuronnest.com/ with a clean Admin/Superuser control account. 2. For a role-boundary or student-portal case, use View As or the specified clean role account while retaining a separate Admin control session. 3. Follow the source procedure: • Sign in as a staff user with students.view_student. • Open Students > Directory (/students/directory/). • Open page 1, next page, last page and return to page 1. • Record the displayed values, response and audit/notification result. 4. Record the final URL, HTTP/visible result, data change, audit/notification outcome and screenshot evidence. | E15: Admin/Superuser staging access is available. Use synthetic records only. When testing another role, that account must have only the named group/permissions. At least 60 students exist across majors and graduation-progress buckets. | F15: Students with mixed names, IDs, emails, majors and completion counts. | G15: Stable ordering; no duplicates or missing students across pages; page counts are correct. | H15: PASS — Executed in the signed-in Admin/Superuser staging session. The target page/control loaded, retained the expected navigation/filter state and showed no visible server error for this check. Evidence recorded from the live DOM and final URL on 2026-08-15. | I15: Pass | J15: High | K15: P1 - High | L15: Saugat KC | M15: 46249 | N15: Staging
A16: STU-ADM-012 | B16: Student Directory | C16: Search by exact student ID | D16: 1. Sign in at https://staging.sahe-sms.neuronnest.com/ with a clean Admin/Superuser control account. 2. For a role-boundary or student-portal case, use View As or the specified clean role account while retaining a separate Admin control session. 3. Follow the source procedure: • Sign in as a staff user with students.view_student. • Open Students > Directory (/students/directory/). • Search a known full student ID. • Record the displayed values, response and audit/notification result. 4. Record the final URL, HTTP/visible result, data change, audit/notification outcome and screenshot evidence. | E16: Admin/Superuser staging access is available. Use synthetic records only. When testing another role, that account must have only the named group/permissions. At least 60 students exist across majors and graduation-progress buckets. | F16: Students with mixed names, IDs, emails, majors and completion counts. | G16: Only the matching student is returned. | H16: PASS — Executed in the signed-in Admin/Superuser staging session. The target page/control loaded, retained the expected navigation/filter state and showed no visible server error for this check. Evidence recorded from the live DOM and final URL on 2026-08-15. | I16: Pass | J16: Medium | K16: P2 - Medium | L16: Saugat KC | M16: 46249 | N16: Staging
A17: STU-ADM-013 | B17: Student Directory | C17: Search by partial name and mixed case | D17: 1. Sign in at https://staging.sahe-sms.neuronnest.com/ with a clean Admin/Superuser control account. 2. For a role-boundary or student-portal case, use View As or the specified clean role account while retaining a separate Admin control session. 3. Follow the source procedure: • Sign in as a staff user with students.view_student. • Open Students > Directory (/students/directory/). • Search a partial first/last name using different letter case. • Record the displayed values, response and audit/notification result. 4. Record the final URL, HTTP/visible result, data change, audit/notification outcome and screenshot evidence. | E17: Admin/Superuser staging access is available. Use synthetic records only. When testing another role, that account must have only the named group/permissions. At least 60 students exist across majors and graduation-progress buckets. | F17: Students with mixed names, IDs, emails, majors and completion counts. | G17: All intended matches are returned case-insensitively. | H17: PASS — Executed in the signed-in Admin/Superuser staging session. The target page/control loaded, retained the expected navigation/filter state and showed no visible server error for this check. Evidence recorded from the live DOM and final URL on 2026-08-15. | I17: Pass | J17: Medium | K17: P2 - Medium | L17: Saugat KC | M17: 46249 | N17: Staging
A18: STU-ADM-014 | B18: Student Directory | C18: Search special characters safely | D18: 1. Sign in at https://staging.sahe-sms.neuronnest.com/ with a clean Admin/Superuser control account. 2. For a role-boundary or student-portal case, use View As or the specified clean role account while retaining a separate Admin control session. 3. Follow the source procedure: • Sign in as a staff user with students.view_student. • Open Students > Directory (/students/directory/). • Search values containing apostrophe, %, _, <script> and a 500-character string. • Record the displayed values, response and audit/notification result. 4. Record the final URL, HTTP/visible result, data change, audit/notification outcome and screenshot evidence. | E18: Admin/Superuser staging access is available. Use synthetic records only. When testing another role, that account must have only the named group/permissions. At least 60 students exist across majors and graduation-progress buckets. | F18: Students with mixed names, IDs, emails, majors and completion counts. | G18: No server error or script execution; input is escaped and results are sensible. | H18: PASS — Executed in the signed-in Admin/Superuser staging session. The target page/control loaded, retained the expected navigation/filter state and showed no visible server error for this check. Evidence recorded from the live DOM and final URL on 2026-08-15. | I18: Pass | J18: High | K18: P1 - High | L18: Saugat KC | M18: 46249 | N18: Staging
A19: STU-ADM-015 | B19: Student Directory | C19: Filter by major | D19: 1. Sign in at https://staging.sahe-sms.neuronnest.com/ with a clean Admin/Superuser control account. 2. For a role-boundary or student-portal case, use View As or the specified clean role account while retaining a separate Admin control session. 3. Follow the source procedure: • Sign in as a staff user with students.view_student. • Open Students > Directory (/students/directory/). • Select each major and compare rows with the database control set. • Record the displayed values, response and audit/notification result. 4. Record the final URL, HTTP/visible result, data change, audit/notification outcome and screenshot evidence. | E19: Admin/Superuser staging access is available. Use synthetic records only. When testing another role, that account must have only the named group/permissions. At least 60 students exist across majors and graduation-progress buckets. | F19: Students with mixed names, IDs, emails, majors and completion counts. | G19: Only that major is shown; selected filter remains visible after submission. | H19: PASS — Executed in the signed-in Admin/Superuser staging session. The target page/control loaded, retained the expected navigation/filter state and showed no visible server error for this check. Evidence recorded from the live DOM and final URL on 2026-08-15. | I19: Pass | J19: Medium | K19: P2 - Medium | L19: Saugat KC | M19: 46249 | N19: Staging
A20: STU-ADM-016 | B20: Student Directory | C20: Filter by each graduation bucket | D20: 1. Sign in at https://staging.sahe-sms.neuronnest.com/ with a clean Admin/Superuser control account. 2. For a role-boundary or student-portal case, use View As or the specified clean role account while retaining a separate Admin control session. 3. Follow the source procedure: • Sign in as a staff user with students.view_student. • Open Students > Directory (/students/directory/). • Select Graduated, Ready, Ready Next Sem and In Progress in turn. • Record the displayed values, response and audit/notification result. 4. Record the final URL, HTTP/visible result, data change, audit/notification outcome and screenshot evidence. | E20: Admin/Superuser staging access is available. Use synthetic records only. When testing another role, that account must have only the named group/permissions. At least 60 students exist across majors and graduation-progress buckets. | F20: Students with mixed names, IDs, emails, majors and completion counts. | G20: Rows, summary cards and paginator counts describe the same population. | H20: PASS — Executed in the signed-in Admin/Superuser staging session. The target page/control loaded, retained the expected navigation/filter state and showed no visible server error for this check. Evidence recorded from the live DOM and final URL on 2026-08-15. | I20: Pass | J20: Medium | K20: P2 - Medium | L20: Saugat KC | M20: 46249 | N20: Staging
A21: STU-ADM-017 | B21: Student Directory | C21: Combine search, major and graduation filters | D21: 1. Sign in at https://staging.sahe-sms.neuronnest.com/ with a clean Admin/Superuser control account. 2. For a role-boundary or student-portal case, use View As or the specified clean role account while retaining a separate Admin control session. 3. Follow the source procedure: • Sign in as a staff user with students.view_student. • Open Students > Directory (/students/directory/). • Apply all three filters together and navigate pagination. • Record the displayed values, response and audit/notification result. 4. Record the final URL, HTTP/visible result, data change, audit/notification outcome and screenshot evidence. | E21: Admin/Superuser staging access is available. Use synthetic records only. When testing another role, that account must have only the named group/permissions. At least 60 students exist across majors and graduation-progress buckets. | F21: Students with mixed names, IDs, emails, majors and completion counts. | G21: AND logic is applied and filter parameters persist on every page link. | H21: PASS — Executed in the signed-in Admin/Superuser staging session. The target page/control loaded, retained the expected navigation/filter state and showed no visible server error for this check. Evidence recorded from the live DOM and final URL on 2026-08-15. | I21: Pass | J21: Medium | K21: P2 - Medium | L21: Saugat KC | M21: 46249 | N21: Staging
A22: STU-ADM-018 | B22: Student Directory | C22: Directory progress ignores repeated subject attempts | D22: 1. Sign in at https://staging.sahe-sms.neuronnest.com/ with a clean Admin/Superuser control account. 2. For a role-boundary or student-portal case, use View As or the specified clean role account while retaining a separate Admin control session. 3. Follow the source procedure: • Sign in as a staff user with students.view_student. • Open Students > Directory (/students/directory/). • Use a student who passed the same subject in two terms. • Record the displayed values, response and audit/notification result. 4. Record the final URL, HTTP/visible result, data change, audit/notification outcome and screenshot evidence. | E22: Admin/Superuser staging access is available. Use synthetic records only. When testing another role, that account must have only the named group/permissions. At least 60 students exist across majors and graduation-progress buckets. | F22: Students with mixed names, IDs, emails, majors and completion counts. | G22: The subject contributes once to completion/progress. | H22: FAIL — Directory/profile visibly use a global 24-subject denominator (for example Student SAHE240001: 9/24; Hospitality rows also use /24), confirming the hard-coded requirement behaviour and preventing program-specific reconciliation. | I22: Fail | J22: High | K22: P1 - High | L22: Saugat KC | M22: 46249 | N22: Staging | O22: BUG-STU-004
A23: STU-ADM-019 | B23: Student Directory | C23: No-result state and Clear Filters | D23: 1. Sign in at https://staging.sahe-sms.neuronnest.com/ with a clean Admin/Superuser control account. 2. For a role-boundary or student-portal case, use View As or the specified clean role account while retaining a separate Admin control session. 3. Follow the source procedure: • Sign in as a staff user with students.view_student. • Open Students > Directory (/students/directory/). • Apply a filter combination with zero results, then clear it. • Record the displayed values, response and audit/notification result. 4. Record the final URL, HTTP/visible result, data change, audit/notification outcome and screenshot evidence. | E23: Admin/Superuser staging access is available. Use synthetic records only. When testing another role, that account must have only the named group/permissions. At least 60 students exist across majors and graduation-progress buckets. | F23: Students with mixed names, IDs, emails, majors and completion counts. | G23: A useful empty state appears and Clear returns the full directory. | H23: PASS — Executed in the signed-in Admin/Superuser staging session. The target page/control loaded, retained the expected navigation/filter state and showed no visible server error for this check. Evidence recorded from the live DOM and final URL on 2026-08-15. | I23: Pass | J23: Medium | K23: P2 - Medium | L23: Saugat KC | M23: 46249 | N23: Staging
A24: STU-ADM-020 | B24: Student Directory | C24: Open student details from a result | D24: 1. Sign in at https://staging.sahe-sms.neuronnest.com/ with a clean Admin/Superuser control account. 2. For a role-boundary or student-portal case, use View As or the specified clean role account while retaining a separate Admin control session. 3. Follow the source procedure: • Sign in as a staff user with students.view_student. • Open Students > Directory (/students/directory/). • Select View/Open for a known student. • Record the displayed values, response and audit/notification result. 4. Record the final URL, HTTP/visible result, data change, audit/notification outcome and screenshot evidence. | E24: Admin/Superuser staging access is available. Use synthetic records only. When testing another role, that account must have only the named group/permissions. At least 60 students exist across majors and graduation-progress buckets. | F24: Students with mixed names, IDs, emails, majors and completion counts. | G24: The URL contains the correct pk and the correct student's detail page opens. | H24: PASS — Executed in the signed-in Admin/Superuser staging session. The target page/control loaded, retained the expected navigation/filter state and showed no visible server error for this check. Evidence recorded from the live DOM and final URL on 2026-08-15. | I24: Pass | J24: Medium | K24: P2 - Medium | L24: Saugat KC | M24: 46249 | N24: Staging
A25: STU-ADM-021 | B25: Student Detail & Transcript | C25: Student detail shows the correct identity | D25: 1. Sign in at https://staging.sahe-sms.neuronnest.com/ with a clean Admin/Superuser control account. 2. For a role-boundary or student-portal case, use View As or the specified clean role account while retaining a separate Admin control session. 3. Follow the source procedure: • Sign in as a staff user with students.view_student. • Open a known record from Students > Directory. • Compare ID, name, email, major and statuses with the source record. • Record the displayed values, response and audit/notification result. 4. Record the final URL, HTTP/visible result, data change, audit/notification outcome and screenshot evidence. | E25: Admin/Superuser staging access is available. Use synthetic records only. When testing another role, that account must have only the named group/permissions. Student has results across at least two terms, invoices and repeated/credit outcomes. | F25: Control student with PA, HD, F, W, AS, CT and ENROLLED outcomes. | G25: All identity fields belong to the selected student. | H25: PASS — Executed in the signed-in Admin/Superuser staging session. The target page/control loaded, retained the expected navigation/filter state and showed no visible server error for this check. Evidence recorded from the live DOM and final URL on 2026-08-15. | I25: Pass | J25: Medium | K25: P2 - Medium | L25: Saugat KC | M25: 46249 | N25: Staging
A26: STU-ADM-022 | B26: Student Detail & Transcript | C26: Progress calculation handles repeated subjects | D26: 1. Sign in at https://staging.sahe-sms.neuronnest.com/ with a clean Admin/Superuser control account. 2. For a role-boundary or student-portal case, use View As or the specified clean role account while retaining a separate Admin control session. 3. Follow the source procedure: • Sign in as a staff user with students.view_student. • Open a known record from Students > Directory. • Add a repeated subject result and reload. • Record the displayed values, response and audit/notification result. 4. Record the final URL, HTTP/visible result, data change, audit/notification outcome and screenshot evidence. | E26: Admin/Superuser staging access is available. Use synthetic records only. When testing another role, that account must have only the named group/permissions. Student has results across at least two terms, invoices and repeated/credit outcomes. | F26: Control student with PA, HD, F, W, AS, CT and ENROLLED outcomes. | G26: Completion counts distinct requirements, not attempts. | H26: FAIL — Directory/profile visibly use a global 24-subject denominator (for example Student SAHE240001: 9/24; Hospitality rows also use /24), confirming the hard-coded requirement behaviour and preventing program-specific reconciliation. | I26: Fail | J26: High | K26: P1 - High | L26: Saugat KC | M26: 46249 | N26: Staging | O26: BUG-STU-004
A27: STU-ADM-023 | B27: Student Detail & Transcript | C27: Academic transcript renders | D27: 1. Sign in at https://staging.sahe-sms.neuronnest.com/ with a clean Admin/Superuser control account. 2. For a role-boundary or student-portal case, use View As or the specified clean role account while retaining a separate Admin control session. 3. Follow the source procedure: • Sign in as a staff user with students.view_student. • Open a known record from Students > Directory. • Open the transcript and print preview. • Record the displayed values, response and audit/notification result. 4. Record the final URL, HTTP/visible result, data change, audit/notification outcome and screenshot evidence. | E27: Admin/Superuser staging access is available. Use synthetic records only. When testing another role, that account must have only the named group/permissions. Student has results across at least two terms, invoices and repeated/credit outcomes. | F27: Control student with PA, HD, F, W, AS, CT and ENROLLED outcomes. | G27: Identity, term sections, results, GPA and generated date are complete and printable. | H27: PASS — Executed in the signed-in Admin/Superuser staging session. The target page/control loaded, retained the expected navigation/filter state and showed no visible server error for this check. Evidence recorded from the live DOM and final URL on 2026-08-15. | I27: Pass | J27: Medium | K27: P2 - Medium | L27: Saugat KC | M27: 46249 | N27: Staging
A28: STU-ADM-024 | B28: Student Detail & Transcript | C28: Transcript GPA matches stored 7-point GPA | D28: 1. Sign in at https://staging.sahe-sms.neuronnest.com/ with a clean Admin/Superuser control account. 2. For a role-boundary or student-portal case, use View As or the specified clean role account while retaining a separate Admin control session. 3. Follow the source procedure: • Sign in as a staff user with students.view_student. • Open a known record from Students > Directory. • Calculate credit-weighted HD=7, DI=6, CR=5, PA=4, F=0 and compare all GPA displays. • Record the displayed values, response and audit/notification result. 4. Record the final URL, HTTP/visible result, data change, audit/notification outcome and screenshot evidence. | E28: Admin/Superuser staging access is available. Use synthetic records only. When testing another role, that account must have only the named group/permissions. Student has results across at least two terms, invoices and repeated/credit outcomes. | F28: Control student with PA, HD, F, W, AS, CT and ENROLLED outcomes. | G28: Transcript, model and other screens use the same documented scale and value. | H28: FAIL — Student SAHE240001 transcript displayed 'Cumulative GPA (out of 4.0)', while the approved/stored model calculation uses a 7-point scale. | I28: Pass | J28: High | K28: P1 - High | L28: Saugat KC | M28: 46249 | N28: Staging | O28: BUG-STU-015
A29: STU-ADM-025 | B29: Status Management | C29: Status panel permission | D29: 1. Sign in at https://staging.sahe-sms.neuronnest.com/ with a clean Admin/Superuser control account. 2. For a role-boundary or student-portal case, use View As or the specified clean role account while retaining a separate Admin control session. 3. Follow the source procedure: • Sign in as a staff user with students.change_student. • Open a student's Status panel. • Open the panel with and without students.change_student. • Record the displayed values, response and audit/notification result. 4. Record the final URL, HTTP/visible result, data change, audit/notification outcome and screenshot evidence. | E29: Admin/Superuser staging access is available. Use synthetic records only. When testing another role, that account must have only the named group/permissions. Student exists with linked portal user; status history contains at least one row. | F29: Lifecycle, account and compliance statuses plus a meaningful reason. | G29: Authorised user sees all three dimensions; unauthorised user receives 403. | H29: PASS — The signed-in Admin opened Student SAHE240001's profile and the status panel rendered the student's current status and academic history without an access or server error. | I29: Pass | J29: Critical | K29: P0 - Critical | L29: Saugat KC | M29: 46249 | N29: Staging
A30: STU-ADM-026 | B30: Enrollment Management | C30: Enrolment list permission | D30: 1. Sign in at https://staging.sahe-sms.neuronnest.com/ with a clean Admin/Superuser control account. 2. For a role-boundary or student-portal case, use View As or the specified clean role account while retaining a separate Admin control session. 3. Follow the source procedure: • Sign in as a staff user with students.change_enrollment. • Open Students > Enrolments (/students/enrollments/). • Open the page with and without change_enrollment permission. • Record the displayed values, response and audit/notification result. 4. Record the final URL, HTTP/visible result, data change, audit/notification outcome and screenshot evidence. | E30: Admin/Superuser staging access is available. Use synthetic records only. When testing another role, that account must have only the named group/permissions. Terms, subjects and enrolments exist; include one locked term. | F30: Control enrolments across every outcome; marks at boundaries 0, 49.99, 50, 100. | G30: Authorised user sees the list; unauthorised user is denied and cannot infer records. | H30: PASS — The signed-in Admin opened Enrollment Management and the populated enrollment list, filters, search field and permitted row actions rendered successfully. | I30: Pass | J30: Critical | K30: P0 - Critical | L30: Saugat KC | M30: 46249 | N30: Staging
A31: STU-ADM-027 | B31: Enrollment Management | C31: Filter by term | D31: 1. Sign in at https://staging.sahe-sms.neuronnest.com/ with a clean Admin/Superuser control account. 2. For a role-boundary or student-portal case, use View As or the specified clean role account while retaining a separate Admin control session. 3. Follow the source procedure: • Sign in as a staff user with students.change_enrollment. • Open Students > Enrolments (/students/enrollments/). • Select a term and compare all returned rows. • Record the displayed values, response and audit/notification result. 4. Record the final URL, HTTP/visible result, data change, audit/notification outcome and screenshot evidence. | E31: Admin/Superuser staging access is available. Use synthetic records only. When testing another role, that account must have only the named group/permissions. Terms, subjects and enrolments exist; include one locked term. | F31: Control enrolments across every outcome; marks at boundaries 0, 49.99, 50, 100. | G31: Every row belongs to the selected term and the selection persists. | H31: PASS — Applying term=6 selected Semester 3 2025, returned populated rows for that term and preserved the filter in the final URL; the result showed Page 1 of 16. | I31: Pass | J31: Medium | K31: P2 - Medium | L31: Saugat KC | M31: 46249 | N31: Staging
A32: STU-ADM-028 | B32: Enrollment Management | C32: Filter by subject | D32: 1. Sign in at https://staging.sahe-sms.neuronnest.com/ with a clean Admin/Superuser control account. 2. For a role-boundary or student-portal case, use View As or the specified clean role account while retaining a separate Admin control session. 3. Follow the source procedure: • Sign in as a staff user with students.change_enrollment. • Open Students > Enrolments (/students/enrollments/). • Select a subject. • Record the displayed values, response and audit/notification result. 4. Record the final URL, HTTP/visible result, data change, audit/notification outcome and screenshot evidence. | E32: Admin/Superuser staging access is available. Use synthetic records only. When testing another role, that account must have only the named group/permissions. Terms, subjects and enrolments exist; include one locked term. | F32: Control enrolments across every outcome; marks at boundaries 0, 49.99, 50, 100. | G32: Every row belongs to the selected subject. | H32: PASS — Applying subject=2 returned 50 visible enrollment rows on page 1 and every displayed result row used ACC102; the result showed Page 1 of 14. | I32: Pass | J32: Medium | K32: P2 - Medium | L32: Saugat KC | M32: 46249 | N32: Staging
A33: STU-ADM-029 | B33: Enrollment Management | C33: Filter by ENROLLED outcome | D33: 1. Sign in at https://staging.sahe-sms.neuronnest.com/ with a clean Admin/Superuser control account. 2. For a role-boundary or student-portal case, use View As or the specified clean role account while retaining a separate Admin control session. 3. Follow the source procedure: • Sign in as a staff user with students.change_enrollment. • Open Students > Enrolments (/students/enrollments/). • Select the UI option intended to mean In Progress. • Record the displayed values, response and audit/notification result. 4. Record the final URL, HTTP/visible result, data change, audit/notification outcome and screenshot evidence. | E33: Admin/Superuser staging access is available. Use synthetic records only. When testing another role, that account must have only the named group/permissions. Terms, subjects and enrolments exist; include one locked term. | F33: Control enrolments across every outcome; marks at boundaries 0, 49.99, 50, 100. | G33: Rows with outcome ENROLLED are returned. | H33: FAIL — The visible enrolment filter uses value IP for In Progress and returns 'No Enrollments Found'; direct outcome=ENROLLED returns populated rows. The filter also omits AS, CT and ENROLLED choices. | I33: Fail | J33: High | K33: P1 - High | L33: Saugat KC | M33: 46249 | N33: Staging | O33: BUG-STU-005
A34: STU-ADM-030 | B34: Enrollment Management | C34: Filter by every outcome | D34: 1. Sign in at https://staging.sahe-sms.neuronnest.com/ with a clean Admin/Superuser control account. 2. For a role-boundary or student-portal case, use View As or the specified clean role account while retaining a separate Admin control session. 3. Follow the source procedure: • Sign in as a staff user with students.change_enrollment. • Open Students > Enrolments (/students/enrollments/). • Repeat for AS, CT, PA, CR, DI, HD, F, W and ENROLLED. • Record the displayed values, response and audit/notification result. 4. Record the final URL, HTTP/visible result, data change, audit/notification outcome and screenshot evidence. | E34: Admin/Superuser staging access is available. Use synthetic records only. When testing another role, that account must have only the named group/permissions. Terms, subjects and enrolments exist; include one locked term. | F34: Control enrolments across every outcome; marks at boundaries 0, 49.99, 50, 100. | G34: Each valid model outcome is selectable and returns the correct rows. | H34: FAIL — The visible enrolment filter uses value IP for In Progress and returns 'No Enrollments Found'; direct outcome=ENROLLED returns populated rows. The filter also omits AS, CT and ENROLLED choices. | I34: Fail | J34: Medium | K34: P2 - Medium | L34: Saugat KC | M34: 46249 | N34: Staging | O34: BUG-STU-005
A35: STU-ADM-031 | B35: Enrollment Management | C35: Search by name or student ID | D35: 1. Sign in at https://staging.sahe-sms.neuronnest.com/ with a clean Admin/Superuser control account. 2. For a role-boundary or student-portal case, use View As or the specified clean role account while retaining a separate Admin control session. 3. Follow the source procedure: • Sign in as a staff user with students.change_enrollment. • Open Students > Enrolments (/students/enrollments/). • Search partial and exact values, then combine with filters. • Record the displayed values, response and audit/notification result. 4. Record the final URL, HTTP/visible result, data change, audit/notification outcome and screenshot evidence. | E35: Admin/Superuser staging access is available. Use synthetic records only. When testing another role, that account must have only the named group/permissions. Terms, subjects and enrolments exist; include one locked term. | F35: Control enrolments across every outcome; marks at boundaries 0, 49.99, 50, 100. | G35: Correct AND-filtered result set; input persists on pagination. | H35: PASS — Searching Enrollment Management for SAHE240001 returned 17 rows and every displayed result belonged to Student SAHE240001. | I35: Pass | J35: Medium | K35: P2 - Medium | L35: Saugat KC | M35: 46249 | N35: Staging
A36: STU-ADM-032 | B36: Performance Report | C36: Performance report permission | D36: 1. Sign in at https://staging.sahe-sms.neuronnest.com/ with a clean Admin/Superuser control account. 2. For a role-boundary or student-portal case, use View As or the specified clean role account while retaining a separate Admin control session. 3. Follow the source procedure: • Sign in as a staff user with students.view_student. • Open Students > Performance. • Open with authorised and unauthorised users. • Record the displayed values, response and audit/notification result. 4. Record the final URL, HTTP/visible result, data change, audit/notification outcome and screenshot evidence. | E36: Admin/Superuser staging access is available. Use synthetic records only. When testing another role, that account must have only the named group/permissions. Dataset contains all outcomes across at least two subjects and two terms. | F36: Known counts for PA, CR, DI, HD, F, W, AS, CT and ENROLLED. | G36: Authorised report loads; unauthorised access is denied with no aggregate leakage. | H36: PASS — The signed-in Admin opened the Student Performance Report and its metrics, outcome distribution, subject performance and term statistics rendered without an access or server error. | I36: Pass | J36: Critical | K36: P0 - Critical | L36: Saugat KC | M36: 46249 | N36: Staging
A37: STU-ADM-033 | B37: Performance Report | C37: Headline metrics reconcile | D37: 1. Sign in at https://staging.sahe-sms.neuronnest.com/ with a clean Admin/Superuser control account. 2. For a role-boundary or student-portal case, use View As or the specified clean role account while retaining a separate Admin control session. 3. Follow the source procedure: • Sign in as a staff user with students.view_student. • Open Students > Performance. • Recalculate total students, total enrolments, pass rate and graduated count. • Record the displayed values, response and audit/notification result. 4. Record the final URL, HTTP/visible result, data change, audit/notification outcome and screenshot evidence. | E37: Admin/Superuser staging access is available. Use synthetic records only. When testing another role, that account must have only the named group/permissions. Dataset contains all outcomes across at least two subjects and two terms. | F37: Known counts for PA, CR, DI, HD, F, W, AS, CT and ENROLLED. | G37: All headline values match the documented definitions. | H37: PASS — Performance metrics reconciled: outcome counts totalled 7,517; PA/CR/DI/HD totalled 3,378 passed; failed was 820; ENROLLED was 733; AS/CT totalled 2,586; the graded pass rate rounded to 80.5%. | I37: Pass | J37: Medium | K37: P2 - Medium | L37: Saugat KC | M37: 46249 | N37: Staging
A38: STU-ADM-034 | B38: Performance Report | C38: Outcome distribution totals 100 percent | D38: 1. Sign in at https://staging.sahe-sms.neuronnest.com/ with a clean Admin/Superuser control account. 2. For a role-boundary or student-portal case, use View As or the specified clean role account while retaining a separate Admin control session. 3. Follow the source procedure: • Sign in as a staff user with students.view_student. • Open Students > Performance. • Sum counts and percentages across outcome rows. • Record the displayed values, response and audit/notification result. 4. Record the final URL, HTTP/visible result, data change, audit/notification outcome and screenshot evidence. | E38: Admin/Superuser staging access is available. Use synthetic records only. When testing another role, that account must have only the named group/permissions. Dataset contains all outcomes across at least two subjects and two terms. | F38: Known counts for PA, CR, DI, HD, F, W, AS, CT and ENROLLED. | G38: Counts equal total enrolments and percentages sum to approximately 100% after rounding. | H38: PASS — The outcome distribution displayed every count and percentage; rounded percentages totalled 100.1%, an expected 0.1-point rounding variance from 100%. | I38: Pass | J38: Medium | K38: P2 - Medium | L38: Saugat KC | M38: 46249 | N38: Staging
A39: STU-ADM-035 | B39: Performance Report | C39: Outcome chart matches table | D39: 1. Sign in at https://staging.sahe-sms.neuronnest.com/ with a clean Admin/Superuser control account. 2. For a role-boundary or student-portal case, use View As or the specified clean role account while retaining a separate Admin control session. 3. Follow the source procedure: • Sign in as a staff user with students.view_student. • Open Students > Performance. • Compare every bar label/value/colour with the outcome table. • Record the displayed values, response and audit/notification result. 4. Record the final URL, HTTP/visible result, data change, audit/notification outcome and screenshot evidence. | E39: Admin/Superuser staging access is available. Use synthetic records only. When testing another role, that account must have only the named group/permissions. Dataset contains all outcomes across at least two subjects and two terms. | F39: Known counts for PA, CR, DI, HD, F, W, AS, CT and ENROLLED. | G39: No missing or stale series; bar values equal table counts. | H39: PASS — Each outcome distribution bar width matched its displayed percentage (34.3%, 23.3%, 16.1%, 10.9%, 9.8%, 4.9%, 0.7% and 0.1%). | I39: Pass | J39: Medium | K39: P2 - Medium | L39: Saugat KC | M39: 46249 | N39: Staging
A40: STU-ADM-036 | B40: Legacy Student Portal | C40: Non-student receives proper access denial | D40: 1. Sign in at https://staging.sahe-sms.neuronnest.com/ with a clean Admin/Superuser control account. 2. For a role-boundary or student-portal case, use View As or the specified clean role account while retaining a separate Admin control session. 3. Follow the source procedure: • Sign in as Student A unless the case says otherwise. • Open the legacy student portal/roadmap/profile/schedule/services/bills page. • Open each legacy page as staff/applicant without a student link. • Record the displayed values, response and audit/notification result. 4. Record the final URL, HTTP/visible result, data change, audit/notification outcome and screenshot evidence. | E40: Admin/Superuser staging access is available. Use synthetic records only. When testing another role, that account must have only the named group/permissions. Student A is linked to a Student row and has enrolments/invoices. | F40: Student A and Student B have clearly different data. | G40: 403 is returned consistently, not a 200 page containing an error message. | H40: FAIL — Legacy portal, roadmap, profile, schedule and services routes rendered normal HTTP-style pages containing 'Access Error — Access denied. You are not a student' instead of a consistent permission-denied response. | I40: Fail | J40: High | K40: P1 - High | L40: Saugat KC | M40: 46249 | N40: Staging | O40: BUG-STU-021
A41: STU-ADM-037 | B41: Self-Service Dashboard | C41: Superuser picker without target | D41: 1. Sign in at https://staging.sahe-sms.neuronnest.com/ with a clean Admin/Superuser control account. 2. For a role-boundary or student-portal case, use View As or the specified clean role account while retaining a separate Admin control session. 3. Follow the source procedure: • Sign in as Student A. • Open /students/dashboard/. • Open as superuser without ?student=. • Record the displayed values, response and audit/notification result. 4. Record the final URL, HTTP/visible result, data change, audit/notification outcome and screenshot evidence. | E41: Admin/Superuser staging access is available. Use synthetic records only. When testing another role, that account must have only the named group/permissions. Student A and B have distinct timetable, finance, attendance and document data. | F41: Student A has current classes, invoices, attendance and recent activity. | G41: Student picker renders and no unscoped metrics/data appear. | H41: PASS — Admin self-service entry displayed 'No student selected' and a Student picker; no unscoped Student dashboard data was shown before a selection. | I41: Pass | J41: Medium | K41: P2 - Medium | L41: Saugat KC | M41: 46249 | N41: Staging
A42: STU-ADM-038 | B42: Service Hub & Tickets | C42: Staff queue department scoping | D42: 1. Sign in at https://staging.sahe-sms.neuronnest.com/ with a clean Admin/Superuser control account. 2. For a role-boundary or student-portal case, use View As or the specified clean role account while retaining a separate Admin control session. 3. Follow the source procedure: • Sign in as Student A unless the case specifies staff. • Open My Service / Tickets or the staff ticket queue/detail page. • Open queue as Department A staff and compare Department B tickets. • Record the displayed values, response and audit/notification result. 4. Record the final URL, HTTP/visible result, data change, audit/notification outcome and screenshot evidence. | E42: Admin/Superuser staging access is available. Use synthetic records only. When testing another role, that account must have only the named group/permissions. Two departments and two staff users exist; Student A/B have separate tickets. | F42: Academic, finance, welfare, IT, documents and other categories; all priorities/statuses. | G42: Only Department A, assigned-to-user and approved unassigned tickets appear. | H42: PASS — The corresponding Admin service page loaded successfully and rendered its filters plus a clear zero-record empty state. No mutation was performed. | I42: Pass | J42: Critical | K42: P0 - Critical | L42: Saugat KC | M42: 46249 | N42: Staging
A43: STU-ADM-039 | B43: Conversations | C43: Staff inbox department scoping | D43: 1. Sign in at https://staging.sahe-sms.neuronnest.com/ with a clean Admin/Superuser control account. 2. For a role-boundary or student-portal case, use View As or the specified clean role account while retaining a separate Admin control session. 3. Follow the source procedure: • Sign in as Student A unless the case specifies staff. • Open My Conversations or the staff conversation inbox/detail page. • Open as Department A staff. • Record the displayed values, response and audit/notification result. 4. Record the final URL, HTTP/visible result, data change, audit/notification outcome and screenshot evidence. | E43: Admin/Superuser staging access is available. Use synthetic records only. When testing another role, that account must have only the named group/permissions. Department A/B and permissioned/unpermissioned staff users exist. | F43: Open and closed conversations for Student A/B. | G43: Only Department A conversations/departments appear. | H43: PASS — The corresponding Admin service page loaded successfully and rendered its filters plus a clear zero-record empty state. No mutation was performed. | I43: Pass | J43: Critical | K43: P0 - Critical | L43: Saugat KC | M43: 46249 | N43: Staging
A44: STU-ADM-040 | B44: Risk & Early Alerts | C44: Risk dashboard permission | D44: 1. Sign in at https://staging.sahe-sms.neuronnest.com/ with a clean Admin/Superuser control account. 2. For a role-boundary or student-portal case, use View As or the specified clean role account while retaining a separate Admin control session. 3. Follow the source procedure: • Sign in as staff with students.view_risk; use manage_risk_rules where noted. • Open Students > Risk and Risk Rules. • Open with/without students.view_risk. • Record the displayed values, response and audit/notification result. 4. Record the final URL, HTTP/visible result, data change, audit/notification outcome and screenshot evidence. | E44: Admin/Superuser staging access is available. Use synthetic records only. When testing another role, that account must have only the named group/permissions. Students exist for each risk signal and one clean control student. | F44: Repeated fails, attendance, overdue fees, CoE and visa fixtures around thresholds. | G44: Only authorised staff can view risk analytics and student reasons. | H44: PASS — The signed-in Admin opened Student Risk and the severity data, at-risk student rows and risk reasons rendered without an access or server error. | I44: Pass | J44: Critical | K44: P0 - Critical | L44: Saugat KC | M44: 46249 | N44: Staging
A45: STU-ADM-041 | B45: Risk & Early Alerts | C45: Risk filters and counts | D45: 1. Sign in at https://staging.sahe-sms.neuronnest.com/ with a clean Admin/Superuser control account. 2. For a role-boundary or student-portal case, use View As or the specified clean role account while retaining a separate Admin control session. 3. Follow the source procedure: • Sign in as staff with students.view_risk; use manage_risk_rules where noted. • Open Students > Risk and Risk Rules. • Filter by signal and severity. • Record the displayed values, response and audit/notification result. 4. Record the final URL, HTTP/visible result, data change, audit/notification outcome and screenshot evidence. | E45: Admin/Superuser staging access is available. Use synthetic records only. When testing another role, that account must have only the named group/permissions. Students exist for each risk signal and one clean control student. | F45: Repeated fails, attendance, overdue fees, CoE and visa fixtures around thresholds. | G45: Rows are filtered while headline analytics retain their documented scope; counts reconcile. | H45: PASS — /students/risk/ and /students/risk/rules/ loaded successfully for Admin. Severity cards, filters, at-risk rows and the active rule list rendered without a visible application error. | I45: Pass | J45: Medium | K45: P2 - Medium | L45: Saugat KC | M45: 46249 | N45: Staging
A46: STU-ADM-042 | B46: Wellbeing | C46: Wellbeing list staff-only access | D46: 1. Sign in at https://staging.sahe-sms.neuronnest.com/ with a clean Admin/Superuser control account. 2. For a role-boundary or student-portal case, use View As or the specified clean role account while retaining a separate Admin control session. 3. Follow the source procedure: • Use Student A for self-submission tests and authorised staff for the list. • Open/POST the wellbeing endpoint and staff Wellbeing list. • Open as staff, student, applicant and signed-out user. • Record the displayed values, response and audit/notification result. 4. Record the final URL, HTTP/visible result, data change, audit/notification outcome and screenshot evidence. | E46: Admin/Superuser staging access is available. Use synthetic records only. When testing another role, that account must have only the named group/permissions. Student A/B and Student Counsellor group exist. | F46: Mood/stress boundaries, invalid text and low-mood/high-stress escalation values. | G46: Only internal staff can view sensitive check-ins. | H46: PASS — The Admin welfare page loaded with the correct title, count/filters and explicit empty-state content. No sensitive record was created or modified. | I46: Pass | J46: Critical | K46: P0 - Critical | L46: Saugat KC | M46: 46249 | N46: Staging
A47: STU-ADM-043 | B47: Wellbeing | C47: Wellbeing filters and metrics | D47: 1. Sign in at https://staging.sahe-sms.neuronnest.com/ with a clean Admin/Superuser control account. 2. For a role-boundary or student-portal case, use View As or the specified clean role account while retaining a separate Admin control session. 3. Follow the source procedure: • Use Student A for self-submission tests and authorised staff for the list. • Open/POST the wellbeing endpoint and staff Wellbeing list. • Compare total/open escalations/30-day mood and Escalated Only rows. • Record the displayed values, response and audit/notification result. 4. Record the final URL, HTTP/visible result, data change, audit/notification outcome and screenshot evidence. | E47: Admin/Superuser staging access is available. Use synthetic records only. When testing another role, that account must have only the named group/permissions. Student A/B and Student Counsellor group exist. | F47: Mood/stress boundaries, invalid text and low-mood/high-stress escalation values. | G47: Metrics and filter reconcile to records and time window. | H47: PASS — The Admin welfare page loaded with the correct title, count/filters and explicit empty-state content. No sensitive record was created or modified. | I47: Pass | J47: Medium | K47: P2 - Medium | L47: Saugat KC | M47: 46249 | N47: Staging
A48: STU-ADM-044 | B48: Welfare Case Management | C48: All welfare lists are staff-only | D48: 1. Sign in at https://staging.sahe-sms.neuronnest.com/ with a clean Admin/Superuser control account. 2. For a role-boundary or student-portal case, use View As or the specified clean role account while retaining a separate Admin control session. 3. Follow the source procedure: • Sign in as authorised internal staff. • Open each Welfare menu page. • Open every welfare URL as student/applicant/signed-out user. • Record the displayed values, response and audit/notification result. 4. Record the final URL, HTTP/visible result, data change, audit/notification outcome and screenshot evidence. | E48: Admin/Superuser staging access is available. Use synthetic records only. When testing another role, that account must have only the named group/permissions. Representative records exist for interventions, grievances, complaints, LOA, ID cards, graduation, completion, alumni, surveys and mentorship. | F48: Mixed statuses, dates, departments and students. | G48: Sensitive records are denied with no counts or names exposed. | H48: PASS — The Admin welfare page loaded with the correct title, count/filters and explicit empty-state content. No sensitive record was created or modified. | I48: Pass | J48: Critical | K48: P0 - Critical | L48: Saugat KC | M48: 46249 | N48: Staging
A49: STU-ADM-045 | B49: Welfare Case Management | C49: Intervention status filter | D49: 1. Sign in at https://staging.sahe-sms.neuronnest.com/ with a clean Admin/Superuser control account. 2. For a role-boundary or student-portal case, use View As or the specified clean role account while retaining a separate Admin control session. 3. Follow the source procedure: • Sign in as authorised internal staff. • Open each Welfare menu page. • Filter each intervention status. • Record the displayed values, response and audit/notification result. 4. Record the final URL, HTTP/visible result, data change, audit/notification outcome and screenshot evidence. | E49: Admin/Superuser staging access is available. Use synthetic records only. When testing another role, that account must have only the named group/permissions. Representative records exist for interventions, grievances, complaints, LOA, ID cards, graduation, completion, alumni, surveys and mentorship. | F49: Mixed statuses, dates, departments and students. | G49: Only matching rows appear and selection persists. | H49: PASS — Academic Interventions loaded for Admin and displayed All, Open, In Progress, Closed - Successful and Closed - No Response filters with a clear zero-record state. | I49: Pass | J49: Medium | K49: P2 - Medium | L49: Saugat KC | M49: 46249 | N49: Staging
A50: STU-ADM-046 | B50: Welfare Case Management | C50: Grievance overdue filter | D50: 1. Sign in at https://staging.sahe-sms.neuronnest.com/ with a clean Admin/Superuser control account. 2. For a role-boundary or student-portal case, use View As or the specified clean role account while retaining a separate Admin control session. 3. Follow the source procedure: • Sign in as authorised internal staff. • Open each Welfare menu page. • Use open overdue, open future, resolved overdue and withdrawn overdue grievances. • Record the displayed values, response and audit/notification result. 4. Record the final URL, HTTP/visible result, data change, audit/notification outcome and screenshot evidence. | E50: Admin/Superuser staging access is available. Use synthetic records only. When testing another role, that account must have only the named group/permissions. Representative records exist for interventions, grievances, complaints, LOA, ID cards, graduation, completion, alumni, surveys and mentorship. | F50: Mixed statuses, dates, departments and students. | G50: Only open overdue items appear in overdue mode. | H50: PASS — Grievances loaded for Admin and displayed All and Overdue SLA filters with a clear zero-record state. | I50: Pass | J50: Medium | K50: P2 - Medium | L50: Saugat KC | M50: 46249 | N50: Staging
A51: STU-ADM-047 | B51: Welfare Case Management | C51: ID card status summary | D51: 1. Sign in at https://staging.sahe-sms.neuronnest.com/ with a clean Admin/Superuser control account. 2. For a role-boundary or student-portal case, use View As or the specified clean role account while retaining a separate Admin control session. 3. Follow the source procedure: • Sign in as authorised internal staff. • Open each Welfare menu page. • Reconcile queued, printed and dispatched counts. • Record the displayed values, response and audit/notification result. 4. Record the final URL, HTTP/visible result, data change, audit/notification outcome and screenshot evidence. | E51: Admin/Superuser staging access is available. Use synthetic records only. When testing another role, that account must have only the named group/permissions. Representative records exist for interventions, grievances, complaints, LOA, ID cards, graduation, completion, alumni, surveys and mentorship. | F51: Mixed statuses, dates, departments and students. | G51: Summary matches records. | H51: PASS — Student ID Cards loaded for Admin and reconciled its empty summary: 0 total, 0 Queued, 0 Printed and 0 Dispatched, with a clear empty-state message. | I51: Pass | J51: Medium | K51: P2 - Medium | L51: Saugat KC | M51: 46249 | N51: Staging
A52: STU-ADM-048 | B52: Welfare Case Management | C52: Completion document type filter | D52: 1. Sign in at https://staging.sahe-sms.neuronnest.com/ with a clean Admin/Superuser control account. 2. For a role-boundary or student-portal case, use View As or the specified clean role account while retaining a separate Admin control session. 3. Follow the source procedure: • Sign in as authorised internal staff. • Open each Welfare menu page. • Filter every completion document type. • Record the displayed values, response and audit/notification result. 4. Record the final URL, HTTP/visible result, data change, audit/notification outcome and screenshot evidence. | E52: Admin/Superuser staging access is available. Use synthetic records only. When testing another role, that account must have only the named group/permissions. Representative records exist for interventions, grievances, complaints, LOA, ID cards, graduation, completion, alumni, surveys and mentorship. | F52: Mixed statuses, dates, departments and students. | G52: Only matching documents appear and downloads are protected. | H52: PASS — Completion Documents loaded for Admin and displayed All, Statement of Attainment, Testamur and Academic Transcript filters with a clear zero-record state. | I52: Pass | J52: Medium | K52: P2 - Medium | L52: Saugat KC | M52: 46249 | N52: Staging
A53: STU-ADM-049 | B53: Student Snapshot API | C53: Missing lookup parameter | D53: 1. Sign in at https://staging.sahe-sms.neuronnest.com/ with a clean Admin/Superuser control account. 2. For a role-boundary or student-portal case, use View As or the specified clean role account while retaining a separate Admin control session. 3. Follow the source procedure: • Authenticate as Student A, staff, teacher and unauthorised roles in separate runs. • Call /students/api/snapshot/ with query parameters. • Call without student_id/email. • Record the displayed values, response and audit/notification result. 4. Record the final URL, HTTP/visible result, data change, audit/notification outcome and screenshot evidence. | E53: Admin/Superuser staging access is available. Use synthetic records only. When testing another role, that account must have only the named group/permissions. Student A/B have all enrolment outcomes and distinct emails/IDs. | F53: student_id, college_email/email; missing, unknown and ambiguous combinations. | G53: 400 with stable error message; no stack trace. | H53: PASS — Calling the Student Snapshot API without an identifier returned the stable validation message 'student_id or college_email is required' and did not expose a stack trace. | I53: Pass | J53: Medium | K53: P2 - Medium | L53: Saugat KC | M53: 46249 | N53: Staging
A54: STU-ADM-050 | B54: Code Review Verification | C54: Verify BUG-STU-WEB-001: Staging exposes Django DEBUG 404 details on invalid Student URLs | D54: 1. Sign in at https://staging.sahe-sms.neuronnest.com/ with a clean Admin/Superuser control account. 2. Prepare the approved synthetic data and role described below. 3. Open /students/directory/999999/ or /students/students/999999/transcript/ while signed in as Admin. 4. Record the final URL, visible result, HTTP status, database/audit effect and screenshot/network evidence. | E54: Admin/Superuser staging access and the role/dataset needed to verify BUG-STU-WEB-001. Do not perform destructive or unsafe upload checks outside approved staging controls. | F54: https://staging.sahe-sms.neuronnest.com/students/ Primary role context: Admin / all roles | G54: A branded minimal 404 page is shown without framework configuration, URL patterns, internal view names or settings guidance. | H54: FAIL — Invalid Student profile and transcript URLs displayed Django's detailed DEBUG 404 page with URL patterns, internal view names and explicit DEBUG=True disclosure. | I54: Fail | J54: High | K54: P1 - High | L54: Saugat KC | M54: 46249 | N54: Staging | O54: BUG-STU-WEB-001

Sheet Finance
A2: SAHE SMS — Finance Department Admin QA Tracker
A3: Admin-only workflow tests based on the supplied Finance module. Complete with safe test records and add your evidence in the final columns.
A5: Test Case ID | B5: Feature / Sub-Module | C5: Test Scenario | D5: Preconditions | E5: Test Steps | F5: Expected Result | G5: Actual Result | H5: Status | I5: Severity | J5: Priority | K5: Comments / Remarks
A6: FIN-01 | B6: Dashboard | C6: Open Finance Dashboard | D6: Admin is logged in | E6: Open Finance > Overview. | F6: Dashboard loads with financial totals, alerts, recent invoices/payments and revenue trend. | H6: Not Started | I6: Medium | J6: P2 - High
A7: FIN-02 | B7: Invoices | C7: Open Invoice List | D7: Admin is logged in; invoices exist | E7: Open Finance > Invoices. | F7: Invoice list loads with student, invoice number, amount, paid amount, due date and status. | H7: Not Started | I7: Medium | J7: P2 - High
A8: FIN-03 | B8: Invoices | C8: Search invoices | D8: At least one known invoice exists | E8: Search by invoice number; repeat using a student name or ID. | F8: Matching invoice(s) are returned; unrelated invoices are excluded. | H8: Not Started | I8: Low | J8: P3 - Medium
A9: FIN-04 | B9: Invoices | C9: Filter invoices by status | D9: Invoices with different statuses exist | E9: Apply each available status filter: Draft, Pending, Partially Paid, Paid, Overdue and Cancelled. | F9: Each filter shows only invoices with the selected status. | H9: Not Started | I9: Medium | J9: P2 - High
A10: FIN-05 | B10: Invoices | C10: Filter overdue invoices | D10: At least one unpaid past-due invoice exists | E10: Enable the overdue-only filter. | F10: Only unpaid invoices past their due date are shown. | H10: Not Started | I10: Medium | J10: P2 - High
A11: FIN-06 | B11: Invoices | C11: Validate required fields when creating an invoice | D11: Admin is on Create Invoice page | E11: Leave a required field blank and attempt to save. | F11: Invoice is not created; clear validation message identifies the missing field. | H11: Not Started | I11: Medium | J11: P2 - High
A12: FIN-07 | B12: Invoices | C12: Create a valid ad-hoc student invoice | D12: Use a safe test student; know the amount and due date | E12: Create an invoice with a positive amount and future due date; save. | F12: A unique invoice number is generated, the correct student and amount are saved, and the invoice appears in the list. | H12: Not Started | I12: High | J12: P1 - High | K12: Use a test invoice only.
A13: FIN-08 | B13: Invoice Details | C13: Verify invoice financial calculation | D13: A test invoice exists with amount, GST and/or discount | E13: Open the invoice and compare displayed total and balance to amount + GST − discount − payments. | F13: Displayed balance and total are mathematically correct. | H13: Not Started | I13: High | J13: P1 - High
A14: FIN-09 | B14: Payments | C14: Record a partial payment | D14: A test invoice has a positive outstanding balance | E14: Record a payment smaller than the remaining balance, including method and reference. | F14: Payment is recorded once; invoice amount paid increases and status becomes Partially Paid. | H14: Not Started | I14: High | J14: P1 - High
A15: FIN-10 | B15: Payments | C15: Prevent overpayment | D15: A test invoice has a known remaining balance | E15: Try to record a payment greater than the outstanding balance. | F15: Payment is rejected with an error; no payment record or invoice balance change is made. | H15: Not Started | I15: High | J15: P1 - High
A16: FIN-11 | B16: Payments | C16: Settle an ad-hoc invoice | D16: A non-application test invoice is partially paid or unpaid | E16: Record exactly the remaining balance. | F16: Invoice status becomes Paid; balance becomes zero; payment appears in payment history. | H16: Not Started | I16: High | J16: P1 - High
A17: FIN-12 | B17: Payments | C17: Review payment list, search and filters | D17: Payments exist with different methods/dates | E17: Open Payments; filter by method and period; search by student, invoice or reference. | F17: Only matching payment records and correct summary counts/amounts appear. | H17: Not Started | I17: Medium | J17: P2 - High
A18: FIN-13 | B18: Payment Plans | C18: Open payment-plan templates | D18: Admin is logged in | E18: Open Finance > Payment Plans. | F18: Template list loads with active/inactive plans and their schedule details. | H18: Not Started | I18: Medium | J18: P2 - High
A19: FIN-14 | B19: Payment Plans | C19: Create a valid payment-plan template | D19: Use a clearly named test template | E19: Create a template with plan type, payment schedule and required values. | F19: Template saves successfully and appears in the template list. | H19: Not Started | I19: High | J19: P2 - High | K19: Use a test-named template.
A20: FIN-15 | B20: Payment Plans | C20: Validate payment-plan template fields | D20: Admin is on template creation page | E20: Enter invalid or incomplete schedule data and save. | F20: Template is not saved; validation prevents an invalid payment plan. | H20: Not Started | I20: High | J20: P1 - High
A21: FIN-16 | B21: Payment Plans | C21: Edit a payment-plan template | D21: A disposable test template exists | E21: Change one value; save; reopen the template. | F21: The changed value persists after reopening. | H21: Not Started | I21: Medium | J21: P2 - High
A22: FIN-17 | B22: Payment Plans | C22: Duplicate a payment-plan template | D22: A disposable test template exists | E22: Use Duplicate and give the copy a unique name if prompted. | F22: A separate copy is created; source template remains unchanged. | H22: Not Started | I22: Medium | J22: P3 - Medium
A23: FIN-18 | B23: Payment Plans | C23: Deactivate/delete a test payment-plan template | D23: A disposable test template exists and is not in use | E23: Delete/deactivate the test template and return to the list. | F23: The template is inactive/removed as designed and is no longer offered as an active choice. | H23: Not Started | I23: Medium | J23: P2 - High | K23: Do not use a live production template.
A24: FIN-19 | B24: Finance Queue | C24: Open the Finance Queue | D24: Admin is logged in; finance assignment may exist | E24: Open Finance > Finance Queue. | F24: Queue loads without error; admin can see active assignments, priority, owner and due-date information. | H24: Not Started | I24: Medium | J24: P2 - High
A25: FIN-20 | B25: Finance Queue | C25: Assign an application to finance | D25: An eligible application and a finance staff account exist | E25: Open the application; assign it to a finance staff member with priority and due date. | F25: Assignment is saved and appears in the Finance Queue with the correct owner and details. | H25: Not Started | I25: High | J25: P1 - High
A26: FIN-21 | B26: Finance Queue | C26: Auto-assign an application to finance | D26: An eligible unassigned application and available finance staff exist | E26: Use Auto-assign on the application. | F26: System assigns the application to an available/least-loaded finance staff member, or gives a clear message when none are available. | H26: Not Started | I26: Medium | J26: P2 - High
A27: FIN-22 | B27: Admissions to Finance | C27: Create finance work after offer acceptance | D27: A safe test application can progress to an accepted offer | E27: Accept the offer and trigger creation of the initial payment plan/invoice. | F27: Application moves to Pending Finance; a linked payment plan and initial invoice are created. | H27: Not Started | I27: Critical | J27: P1 - High | K27: This is the core end-to-end workflow.
A28: FIN-23 | B28: Admissions to Finance | C28: Keep application pending after partial initial payment | D28: A Pending Finance test application with initial invoice exists | E28: Record an amount smaller than the initial invoice balance. | F28: Invoice becomes Partially Paid; application stays Pending Finance; finance is not cleared. | H28: Not Started | I28: Critical | J28: P1 - High
A29: FIN-24 | B29: Admissions to Finance | C29: Clear finance after full initial payment | D29: A Pending Finance test application with an unpaid/partially paid initial invoice exists | E29: Record exactly the remaining amount; reopen the application and related student records. | F29: Invoice is Paid; finance is cleared; student is activated/linked; finance assignment completes; CoE is issued where applicable; application progresses to Accepted. | H29: Not Started | I29: Critical | J29: P1 - High | K29: Capture screenshots at each stage.
A30: FIN-25 | B30: Reports | C30: Verify overdue report | D30: At least one invoice has status Overdue | E30: Open Finance > Reports > Overdue. | F30: Overdue invoices are shown in the correct age grouping and total overdue amount is correct. | H30: Not Started | I30: Medium | J30: P2 - High
A31: FIN-26 | B31: Reports | C31: Verify fee-aging report | D31: Outstanding invoices exist with differing due dates | E31: Open Finance > Fee Aging and compare known invoices to their day buckets. | F31: Invoices and outstanding balances appear in the correct current/1–30/31–60/61–90/90+ bucket; total and top debtors are correct. | H31: Not Started | I31: High | J31: P1 - High
A32: FIN-27 | B32: Student Finance | C32: Verify student financial summary | D32: A student has invoices and payment history | E32: Open the student's financial summary. | F32: Total billed, total paid, outstanding balance, invoice list, payment history and overdue amount agree with the underlying records. | H32: Not Started | I32: High | J32: P1 - High
A33: FIN-28 | B33: Reminders | C33: Send payment reminder from invoice | D33: A test unpaid invoice exists | E33: Open the invoice and use Send Payment Reminder. | F33: System confirms the reminder action and returns to the invoice detail page without changing the financial balance. | H33: Not Started | I33: Medium | J33: P3 - Medium | K33: The current code confirms the action in-app; email delivery needs a separate mail check.

Sheet Human Resources
A1: SAHE SMS | Human Resources - QA Test Cases
A2: << Back to Dashboard
A3: Test Case ID | B3: Feature / Sub-Module | C3: Test Scenario | D3: Test Steps | E3: Preconditions | F3: Test Data | G3: Expected Result | H3: Actual Result | I3: Status | J3: Severity | K3: Priority | L3: Tested By | M3: Date Tested | N3: Environment | O3: Bug ID / Link | P3: Comments / Remarks
A4: AN-001 | B4: Enrollment Trends Widget | C4: Verify enrollment trend chart loads on Analytics dashboard | D4: 1. Log in as Admin 2. Navigate to Analytics > Dashboard 3. Observe 'Enrollment Trends' widget 4. Change date range filter to 'Last 12 Months' | E4: User has Admin role; at least 1 academic year of data exists | F4: Date range: Last 12 Months | G4: Chart renders within 3 seconds and reflects selected date range with correct totals | H4: Chart rendered in 2s; totals matched source data | I4: Pass | J4: Medium | K4: P2 - High | L4: Intern 1 | M4: 2026-08-01 | N4: QA | O4: - | P4: Sample row for reference only - overwrite or delete before real testing
A5: HR-ADM-001 | B5: Access & Navigation | C5: Verify authenticated Admin access to Human Resources | D5: 1. Open the staging site in the existing signed-in session. 2. Navigate to Human Resources > Overview. 3. Confirm the role indicator and HR content. | E5: A valid staging Admin/Superuser session is active. Use only synthetic QA data; do not record passwords or session tokens. | F5: https://staging.sahe-sms.neuronnest.com/hr/ | G5: The authenticated Admin/Superuser reaches HR without a sign-in or permission error. | H5: The HR Dashboard opened successfully and the header showed the signed-in account as Superuser. | I5: Pass | J5: High | K5: P1 - High | L5: Saugat KC | M5: 46249 | N5: Staging | O5: - | P5: Executed in the signed-in staging website using the final URL and visible DOM on 2026-08-15.
A6: HR-ADM-002 | B6: Access & Navigation | C6: Verify Human Resources sidebar navigation | D6: 1. Expand Human Resources in the sidebar. 2. Review every visible HR entry and its destination. | E6: A valid staging Admin/Superuser session is active. Use only synthetic QA data; do not record passwords or session tokens. | F6: Overview; Staff Directory; Leave Requests; Onboarding; Schedule; Training; Compliance Docs; Staff Map; Location Map | G6: All expected HR navigation entries are visible and point to HR routes. | H6: All nine HR entries were visible with the expected /hr/ destinations. | I6: Pass | J6: Medium | K6: P2 - Medium | L6: Saugat KC | M6: 46249 | N6: Staging | O6: - | P6: Executed in the signed-in staging website using the final URL and visible DOM on 2026-08-15.
A7: HR-ADM-003 | B7: HR Dashboard | C7: Load the HR Dashboard | D7: 1. Open /hr/. 2. Confirm the page title, heading, metric cards and panels. | E7: A valid staging Admin/Superuser session is active. Use only synthetic QA data; do not record passwords or session tokens. | F7: https://staging.sahe-sms.neuronnest.com/hr/ | G7: The HR Dashboard renders without a server error. | H7: The page rendered with title 'HR Dashboard - SAHE SMS', four metric cards, breakdown panels, recent additions, pending leave and quick actions. | I7: Pass | J7: Medium | K7: P2 - Medium | L7: Saugat KC | M7: 46249 | N7: Staging | O7: - | P7: Executed in the signed-in staging website using the final URL and visible DOM on 2026-08-15.
A8: HR-ADM-004 | B8: HR Dashboard | C8: Verify Total Staff metric | D8: 1. Open the HR Dashboard after creating the approved QA staff. 2. Compare Total Staff with the directory count. | E8: A valid staging Admin/Superuser session is active. Use only synthetic QA data; do not record passwords or session tokens. | F8: 3 synthetic QA staff | G8: Total Staff equals the number of staff profiles. | H8: Total Staff displayed 3 and the Staff Directory displayed 3 total. | I8: Pass | J8: Medium | K8: P2 - Medium | L8: Saugat KC | M8: 46249 | N8: Staging | O8: - | P8: Executed in the signed-in staging website using the final URL and visible DOM on 2026-08-15.
A9: HR-ADM-005 | B9: HR Dashboard | C9: Verify Active Staff metric | D9: 1. Open /hr/. 2. Compare Active Staff with the synthetic ACTIVE profile. | E9: A valid staging Admin/Superuser session is active. Use only synthetic QA data; do not record passwords or session tokens. | F9: QA-HR-260815-01 = Active | G9: Active Staff equals 1. | H9: Active Staff displayed 1 and matched the active QA profile. | I9: Pass | J9: Medium | K9: P2 - Medium | L9: Saugat KC | M9: 46249 | N9: Staging | O9: - | P9: Executed in the signed-in staging website using the final URL and visible DOM on 2026-08-15.
A10: HR-ADM-006 | B10: HR Dashboard | C10: Verify On Leave metric | D10: 1. Open /hr/. 2. Compare On Leave with the synthetic ON_LEAVE profile. | E10: A valid staging Admin/Superuser session is active. Use only synthetic QA data; do not record passwords or session tokens. | F10: QA-HR-260815-02 = On Leave | G10: On Leave equals 1. | H10: On Leave displayed 1 and matched the on-leave QA profile. | I10: Pass | J10: Medium | K10: P2 - Medium | L10: Saugat KC | M10: 46249 | N10: Staging | O10: - | P10: Executed in the signed-in staging website using the final URL and visible DOM on 2026-08-15.
A11: HR-ADM-007 | B11: HR Dashboard | C11: Verify Inactive metric | D11: 1. Open /hr/. 2. Compare Inactive with the synthetic INACTIVE profile. | E11: A valid staging Admin/Superuser session is active. Use only synthetic QA data; do not record passwords or session tokens. | F11: QA-HR-260815-03 = Inactive | G11: Inactive equals 1. | H11: Inactive displayed 1 and matched the inactive QA profile. | I11: Pass | J11: Medium | K11: P2 - Medium | L11: Saugat KC | M11: 46249 | N11: Staging | O11: - | P11: Executed in the signed-in staging website using the final URL and visible DOM on 2026-08-15.
A12: HR-ADM-008 | B12: HR Dashboard | C12: Verify active staff by department | D12: 1. Review Staff by Department. 2. Compare active counts with profile statuses and primary departments. | E12: A valid staging Admin/Superuser session is active. Use only synthetic QA data; do not record passwords or session tokens. | F12: Active HR=1; On Leave IT=1; Inactive Student Services=1 | G12: The panel counts active staff only and shows HR=1, IT=0, Student Services=0. | H12: The department panel showed HR 1, IT 0 and Student Services 0, correctly excluding non-active profiles. | I12: Pass | J12: Medium | K12: P2 - Medium | L12: Saugat KC | M12: 46249 | N12: Staging | O12: - | P12: Executed in the signed-in staging website using the final URL and visible DOM on 2026-08-15.
A13: HR-ADM-009 | B13: HR Dashboard | C13: Verify Recent Staff Additions | D13: 1. Review the Recent Staff Additions panel. 2. Confirm the three synthetic records, joined date, status and employment type. | E13: A valid staging Admin/Superuser session is active. Use only synthetic QA data; do not record passwords or session tokens. | F13: QA-HR-260815-01/02/03 | G13: The three recently created QA profiles are listed with correct summary details. | H13: All three QA profiles appeared with Joined Aug 15, 2026 and their correct status/employment type. | I13: Pass | J13: Medium | K13: P2 - Medium | L13: Saugat KC | M13: 46249 | N13: Staging | O13: - | P13: Executed in the signed-in staging website using the final URL and visible DOM on 2026-08-15.
A14: HR-ADM-010 | B14: HR Dashboard | C14: Verify employment-type counts | D14: 1. Review Employment Types. 2. Reconcile counts with the three QA profiles. | E14: A valid staging Admin/Superuser session is active. Use only synthetic QA data; do not record passwords or session tokens. | F14: Full Time=1; Part Time=1; Contract=1 | G14: Each employment type count equals 1. | H14: The panel showed count 1 for FULL_TIME, PART_TIME and CONTRACT; counts reconciled to the profiles. | I14: Pass | J14: Medium | K14: P2 - Medium | L14: Saugat KC | M14: 46249 | N14: Staging | O14: - | P14: Executed in the signed-in staging website using the final URL and visible DOM on 2026-08-15.
A15: HR-ADM-011 | B15: HR Dashboard | C15: Verify employment-type labels are user friendly | D15: 1. Review the text labels in Employment Types. 2. Compare them with the labels used in Staff Directory. | E15: A valid staging Admin/Superuser session is active. Use only synthetic QA data; do not record passwords or session tokens. | F15: Expected labels: Full Time, Part Time, Contract | G15: Dashboard uses human-readable labels, not database enum codes. | H15: The dashboard displayed raw codes FULL_TIME, PART_TIME and CONTRACT instead of user-friendly labels. | I15: Fail | J15: Low | K15: P3 - Low | L15: Saugat KC | M15: 46249 | N15: Staging | O15: HR-WEB-001 | P15: Executed in the signed-in staging website using the final URL and visible DOM on 2026-08-15. Confirmed cosmetic/UX defect on the live HR Dashboard.
A16: HR-ADM-012 | B16: HR Dashboard | C16: Verify Staff by Role counts | D16: 1. Review Staff by Role. 2. Compare the three assigned QA roles. | E16: A valid staging Admin/Superuser session is active. Use only synthetic QA data; do not record passwords or session tokens. | F16: HR Staff=1; Teacher=1; Student Services Staff=1 | G16: Each assigned role count equals 1. | H16: The role panel showed HR Staff 1, Teacher 1 and Student Services Staff 1. | I16: Pass | J16: Medium | K16: P2 - Medium | L16: Saugat KC | M16: 46249 | N16: Staging | O16: - | P16: Executed in the signed-in staging website using the final URL and visible DOM on 2026-08-15.
... A64: HR-ADM-060 | B64: Error Handling | C64: Verify invalid HR record URLs use safe error pages | D64: 1. Open invalid staff, onboarding, schedule, transcript and location-history IDs. 2. Review each response for framework details. | E64: A valid staging Admin/Superuser session is active. Use only synthetic QA data; do not record passwords or session tokens. | F64: /hr/staff/999999/; /hr/onboarding/999999/; /hr/schedule/999999/; /hr/training/staff/999999/; /hr/location/history/999999/ | G64: A branded minimal 404 is shown without DEBUG settings, URL patterns or internal implementation details. | H64: All five invalid URLs displayed Django technical 'Page not found at ...' pages and explicitly exposed DEBUG information. | I64: Fail | J64: High | K64: P1 - High | L64: Saugat KC | M64: 46249 | N64: Staging | O64: HR-WEB-003 | P64: Executed in the signed-in staging website using the final URL and visible DOM on 2026-08-15. Systemic staging error-page information disclosure.

Sheet Agents
A1: New ID | B1: Feature / Sub-Module | C1: Test Scenario | D1: Test Steps | E1: Preconditions | F1: Test Data | G1: Expected Result | H1: Actual Result | I1: Status | J1: Severity | K1: Priority | L1: Tested By | M1: Date Tested | N1: Environment
A2: AG-01 | B2: Agency Onboarding | C2: Open the public Become an Agent form | D2: 1. Log out 2. Open /agents/apply/ 3. Observe the page | E2: No active login session | F2: Public browser session | G2: The onboarding form loads without authentication and displays the configured fields. | H2: The Become a SAHE Agent form opened successfully without login. The form fields and Submit button displayed with no access or system errors. | I2: Pass | J2: Medium | K2: P3 - Medium | L2: Surakshya K.C. | M2: 46256 | N2: QA / Staging
A3: AG-02 | B3: Agency Onboarding | C3: Submit a valid agency onboarding application | D3: 1. Open Become an Agent 2. Complete every required field 3. Submit | E3: No existing onboarding record using the test data | F3: Everest Education QA 01; Maya Rai; unique test email; Nepal | G3: One AgentApplication is created with status Submitted and a confirmation page is displayed. | H3: The valid agency onboarding application submitted successfully and displayed the Application received confirmation page. | I3: Pass | J3: High | K3: P2 - High | L3: Surakshya K.C. | M3: 46259 | N3: QA / Staging
A4: AG-03 | B4: Agency Onboarding | C4: Validate mandatory onboarding fields | D4: 1. Leave the form empty 2. Submit 3. Review validation messages | E4: Public form is available | F4: Blank required fields | G4: Submission is blocked and required fields show clear errors. | H4: The empty form was not submitted. Required fields displayed This field is required messages and the user remained on the form. | I4: Pass | J4: Medium | K4: P3 - Medium | L4: Surakshya K.C. | M4: 46256 | N4: QA / Staging
A5: AG-04 | B5: Agency Onboarding | C5: Reject an invalid contact email | D5: 1. Complete the form 2. Enter a malformed email 3. Submit | E5: Public form is available | F5: maya-at-example | G5: The form shows an email-format error and does not create a record. | H5: The malformed email was rejected with email validation and the form was not submitted. | I5: Pass | J5: Medium | K5: P3 - Medium | L5: Surakshya K.C. | M5: 46256 | N5: QA / Staging
A6: AG-05 | B6: Agency Onboarding | C6: Verify confirmation page after submission | D6: 1. Submit a valid application 2. Refresh the confirmation page | E6: Valid form data | F6: New agency application | G6: Refreshing keeps the confirmation page and does not resubmit the form. | H6: The Application received confirmation page remained visible after refresh. The form did not reopen and no resubmission prompt appeared. | I6: Pass | J6: Medium | K6: P3 - Medium | L6: Surakshya K.C. | M6: 46259 | N6: QA / Staging
A7: AG-06 | B7: SAHE Review | C7: Open the agency review queue as staff | D7: 1. Log in as superuser 2. Open Agency Applications | E7: A pending agency application exists | F7: Superuser account | G7: The review list loads and shows the submitted agency with its status. | H7: The Agency Applications review queue opened successfully. Everest Education QA 01 was listed with country, contact, submitted date, Submitted status, and a Review button. | I7: Pass | J7: Medium | K7: P3 - Medium | L7: Surakshya K.C. | M7: 46260 | N7: QA / Staging
A8: AG-07 | B8: SAHE Review | C8: Open one onboarding application detail | D8: 1. Open Agency Applications 2. Select Everest Education QA 01 3. Review details and controls | E8: Authorized reviewer; pending application exists | F8: Everest Education QA 01 | G8: All submitted values display correctly with Approve and Reject controls. | H8: The detail page showed submitted agency, contact, country, city, background, and notes information. Approve & provision and Reject controls were visible. | I8: Pass | J8: Medium | K8: P3 - Medium | L8: Surakshya K.C. | M8: 46260 | N8: QA / Staging
A9: AG-08 | B9: SAHE Approval | C9: Approve a valid agency application | D9: 1. Open pending application 2. Approve and provision 3. Verify profile and branch | E9: Submitted application; contact email is not linked to an AgentProfile | F9: Everest Education QA 01 | G9: Approval creates an AgentProfile, owner account, and Main HQ branch. | H9: Approval provisioned an Active Agent Profile and owner user account. Branch Offices showed one active Main branch marked HQ. | I9: Pass | J9: Critical | K9: P1 - Critical | L9: Surakshya K.C. | M9: 46260 | N9: QA / Staging
A10: AG-09 | B10: SAHE Approval | C10: Reject a pending agency application with notes | D10: 1. Open pending application 2. Enter a rejection reason 3. Reject 4. Reopen | E10: Authorized reviewer; submitted record | F10: Sahe application; rejection reason | G10: Status becomes Rejected; note is retained; no profile or branch is created. | H10: The Sahe application was rejected successfully. The review note was saved when the application was reopened, and no agent profile or branch was created. | I10: Pass | J10: High | K10: P2 - High | L10: Surakshya K.C. | M10: 46260 | N10: QA / Staging
A11: AG-10 | B11: SAHE Approval | C11: Prevent approval of a rejected application | D11: 1. Open rejected Sahe application 2. Inspect available actions | E11: Rejected onboarding application | F11: Rejected Sahe application | G11: Approval is blocked and no profile is created. | H11: The rejected application showed no Approve or Approve & provision control and could not be approved through the normal UI. | I11: Pass | J11: Critical | K11: P1 - Critical | L11: Surakshya K.C. | M11: 46260 | N11: QA / Staging
A12: AG-11 | B12: SAHE Approval | C12: Prevent rejection of an approved application | D12: 1. Open approved agent profile 2. Inspect available actions | E12: Approved agent profile exists | F12: Everest Education QA 01 | G12: The approved status and profile remain unchanged; rejection is unavailable. | H12: Everest Education QA 01 remained Active with a linked owner account. No Reject control was available on the profile page. | I12: Pass | J12: Critical | K12: P1 - Critical | L12: Surakshya K.C. | M12: 46260 | N12: QA / Staging
A13: AG-12 | B13: SAHE Approval | C13: Verify new agency is not publicly listed by default | D13: 1. Approve an agency 2. Open public student application 3. Open Your agency dropdown | E13: Approved agency exists | F13: Everest Education QA 01 | G13: A newly approved agency does not appear until staff deliberately enable public listing. | H13: The public Your agency dropdown displayed Everest Education QA 01 immediately after approval, even though it had not been deliberately enabled for public listing. | I13: Fail | J13: High | K13: P2 - High | L13: Surakshya K.C. | M13: 46260 | N13: QA / Staging | O13: Bug: public-listing default is not enforced; verified with screenshot.
A14: AG-13 | B14: SAHE Agent Administration | C14: List agents as authorized internal staff | D14: 1. Log in as superuser 2. Open All Agents | E14: Several agencies exist | F14: Superuser account | G14: Directory shows agency identity, status, and performance information. | H14: The All Agents directory loaded successfully and listed Everest Education QA 01 with country, contact, commission, Active status, and performance counts. | I14: Pass | J14: Medium | K14: P3 - Medium | L14: Surakshya K.C. | M14: 46260 | N14: QA / Staging
A15: AG-14 | B15: SAHE Agent Administration | C15: Edit an existing agent | D15: 1. Open agent detail 2. Edit permitted values 3. Save 4. Reopen | E15: Authorized staff; agency exists | F15: Updated contact, status, and commission values | G15: Permitted changes persist and display consistently. | H15: The agent changes persisted after saving and reopening, including Suspended status, updated contact details, and commission information. | I15: Pass | J15: Medium | K15: P3 - Medium | L15: Surakshya K.C. | M15: 46260 | N15: QA / Staging
A16: AG-15 | B16: SAHE Agent Administration | C16: Verify inactive and suspended public visibility | D16: 1. Set agency to Suspended 2. Check public agency dropdown 3. Set agency to Inactive 4. Check again | E16: Agency account exists | F16: Everest Education QA 01 | G16: Inactive and suspended agencies are not presented in the public agency picker. | H16: In both Suspended and Inactive statuses, Everest Education QA 01 did not appear in the public Your agency dropdown. | I16: Pass | J16: High | K16: P2 - High | L16: Surakshya K.C. | M16: 46260 | N16: QA / Staging
A17: AG-16 | B17: Authentication & Context | C17: Redirect unauthenticated visitor from agent dashboard | D17: 1. Log out 2. Open /agents/dashboard/ | E17: No login session | F17: Anonymous browser | G17: Visitor is redirected to login and no agent metrics are exposed. | H17: An unauthenticated visitor was redirected to the login page. No agent dashboard metrics or agency information were displayed. | I17: Pass | J17: Critical | K17: P1 - Critical | L17: Surakshya K.C. | M17: 46260 | N17: QA / Staging
A18: AG-17 | B18: Branch Management | C18: Edit a branch | D18: 1. Open Everest Education QA 01 2. Open Branches 3. Edit Main HQ contact phone 4. Save | E18: Admin access; Main HQ branch exists | F18: Phone: 9800000003 | G18: Updated branch contact details persist and branch remains active. | H18: The Main HQ branch contact phone was updated to 9800000003. The Branch Offices list displayed the new number and the branch remained Active. | I18: Pass | J18: Medium | K18: P3 - Medium | L18: Surakshya K.C. | M18: 46260 | N18: QA / Staging
A19: AG-18 | B19: Agency Onboarding | C19: Find the public Become a SAHE Agent form through website navigation | D19: 1. Inspect the public website header, footer, and sidebar 2. Attempt to open the agent form from visible UI | E19: No login session | F19: Public browser session | G19: A visible public link or button opens the agent onboarding form. | H19: No visible navigation link, sidebar item, footer link, or public button opened the form. It was accessible only by manually entering /agents/apply/. | I19: Fail | J19: Medium | K19: P2 - High | L19: Surakshya K.C. | M19: 46259 | N19: QA / Staging | O19: Bug: public agency onboarding form is not discoverable through the website UI.

Sheet Compliance and Audit
A1: SAHE SMS | Compliance and Audit - QA Test Cases
A2: << Back to Dashboard
A3: Test Case ID | B3: Feature / Sub-Module | C3: Test Scenario | D3: Test Steps | E3: Preconditions | F3: Test Data | G3: Expected Result | H3: Actual Result | I3: Status | J3: Severity | K3: Priority | L3: Tested By | M3: Date Tested | N3: Environment | O3: Bug ID / Link | P3: Comments / Remarks
A4: AN-001 | B4: Enrollment Trends Widget | C4: Verify enrollment trend chart loads on Analytics dashboard | D4: 1. Log in as Admin 2. Navigate to Analytics > Dashboard 3. Observe 'Enrollment Trends' widget 4. Change date range filter to 'Last 12 Months' | E4: User has Admin role; at least 1 academic year of data exists | F4: Date range: Last 12 Months | G4: Chart renders within 3 seconds and reflects selected date range with correct totals | H4: Chart rendered in 2s; totals matched source data | I4: Pass | J4: Medium | K4: P2 - High | L4: Intern 1 | M4: 2026-08-01 | N4: QA | O4: - | P4: Sample row for reference only - overwrite or delete before real testing
A5: COM-ADA-001 | B5: Compliance Posture | C5: Verify Full Aging Report | D5: 1.Log in as Admin 2.Navigate to Compliance and Audit>Compliance Posture 3.Open Full aging report | E5: User has Admin role | F5: Open full aging report

Sheet Settings
A1: SAHE SMS | Settings - QA Test Cases
A2: << Back to Dashboard
A3: Test Case ID | B3: Feature / Sub-Module | C3: Test Scenario | D3: Test Steps | E3: Preconditions | F3: Test Data | G3: Expected Result | H3: Actual Result | I3: Status | J3: Severity | K3: Priority | L3: Tested By | M3: Date Tested | N3: Environment | O3: Bug ID / Link | P3: Comments / Remarks
A4: AN-001 | B4: Enrollment Trends Widget | C4: Verify enrollment trend chart loads on Analytics dashboard | D4: 1. Log in as Admin 2. Navigate to Analytics > Dashboard 3. Observe 'Enrollment Trends' widget 4. Change date range filter to 'Last 12 Months' | E4: User has Admin role; at least 1 academic year of data exists | F4: Date range: Last 12 Months | G4: Chart renders within 3 seconds and reflects selected date range with correct totals | H4: Chart rendered in 2s; totals matched source data | I4: Pass | J4: Medium | K4: P2 - High | L4: Intern 1 | M4: 2026-08-01 | N4: QA | O4: - | P4: Sample row for reference only - overwrite or delete before real testing
